{
  "cache_version": 4,
  "generated_at": "2026-03-31T06:21:47.104009+00:00",
  "bars": [
    {
      "time": 1735516800,
      "open": 803.31,
      "high": 803.31,
      "low": 803.31,
      "close": 803.31,
      "volume": 2
    },
    {
      "time": 1735689600,
      "open": 803.31,
      "high": 807.3,
      "low": 803.31,
      "close": 807.3,
      "volume": 14
    },
    {
      "time": 1735776000,
      "open": 807.25,
      "high": 807.3,
      "low": 793.38,
      "close": 793.38,
      "volume": 169
    },
    {
      "time": 1735862400,
      "open": 799.42,
      "high": 807.2,
      "low": 799.42,
      "close": 802.56,
      "volume": 74
    },
    {
      "time": 1736121600,
      "open": 803.31,
      "high": 808.25,
      "low": 779.36,
      "close": 793.53,
      "volume": 202
    },
    {
      "time": 1736208000,
      "open": 803.31,
      "high": 803.31,
      "low": 760.4,
      "close": 768.93,
      "volume": 503
    },
    {
      "time": 1736294400,
      "open": 770.38,
      "high": 796.12,
      "low": 770.38,
      "close": 794.48,
      "volume": 127
    },
    {
      "time": 1736380800,
      "open": 799.32,
      "high": 799.32,
      "low": 775.37,
      "close": 799.27,
      "volume": 121
    },
    {
      "time": 1736467200,
      "open": 793.28,
      "high": 793.28,
      "low": 768.38,
      "close": 778.31,
      "volume": 130
    },
    {
      "time": 1736726400,
      "open": 764.34,
      "high": 798.12,
      "low": 764.34,
      "close": 783.2,
      "volume": 426
    },
    {
      "time": 1736812800,
      "open": 760.4,
      "high": 797.32,
      "low": 759.7,
      "close": 796.17,
      "volume": 506
    },
    {
      "time": 1736899200,
      "open": 772.27,
      "high": 806.2,
      "low": 772.27,
      "close": 778.21,
      "volume": 36
    },
    {
      "time": 1736985600,
      "open": 798.32,
      "high": 798.32,
      "low": 769.43,
      "close": 785.94,
      "volume": 215
    },
    {
      "time": 1737072000,
      "open": 795.32,
      "high": 795.32,
      "low": 795.22,
      "close": 795.32,
      "volume": 3
    },
    {
      "time": 1737331200,
      "open": 793.33,
      "high": 798.32,
      "low": 773.37,
      "close": 789.99,
      "volume": 244
    },
    {
      "time": 1737417600,
      "open": 795.32,
      "high": 795.32,
      "low": 771.42,
      "close": 775.96,
      "volume": 192
    },
    {
      "time": 1737504000,
      "open": 776.36,
      "high": 788.34,
      "low": 768.48,
      "close": 775.12,
      "volume": 34
    },
    {
      "time": 1737590400,
      "open": 775.12,
      "high": 793.28,
      "low": 766.68,
      "close": 785.59,
      "volume": 208
    },
    {
      "time": 1737676800,
      "open": 788.34,
      "high": 788.34,
      "low": 761.4,
      "close": 785.15,
      "volume": 212
    },
    {
      "time": 1737936000,
      "open": 793.33,
      "high": 793.33,
      "low": 770.58,
      "close": 770.58,
      "volume": 90
    },
    {
      "time": 1738108800,
      "open": 796.27,
      "high": 796.27,
      "low": 762.84,
      "close": 784.7,
      "volume": 126
    },
    {
      "time": 1738195200,
      "open": 790.33,
      "high": 790.33,
      "low": 752.41,
      "close": 756.31,
      "volume": 62
    },
    {
      "time": 1738281600,
      "open": 789.24,
      "high": 789.24,
      "low": 768.38,
      "close": 788.19,
      "volume": 26
    },
    {
      "time": 1738368000,
      "open": 768.38,
      "high": 768.38,
      "low": 743.43,
      "close": 758.4,
      "volume": 151
    },
    {
      "time": 1738540800,
      "open": 778.36,
      "high": 778.36,
      "low": 738.44,
      "close": 738.44,
      "volume": 111
    },
    {
      "time": 1738627200,
      "open": 739.44,
      "high": 768.33,
      "low": 738.44,
      "close": 755.21,
      "volume": 31
    },
    {
      "time": 1738713600,
      "open": 777.36,
      "high": 777.36,
      "low": 757.4,
      "close": 757.4,
      "volume": 9
    },
    {
      "time": 1738800000,
      "open": 776.36,
      "high": 797.32,
      "low": 757.4,
      "close": 791.13,
      "volume": 412
    },
    {
      "time": 1738886400,
      "open": 758.4,
      "high": 787.34,
      "low": 758.4,
      "close": 765.39,
      "volume": 40
    },
    {
      "time": 1739145600,
      "open": 765.89,
      "high": 797.32,
      "low": 765.89,
      "close": 765.89,
      "volume": 1280
    },
    {
      "time": 1739232000,
      "open": 757.95,
      "high": 765.89,
      "low": 757.9,
      "close": 757.9,
      "volume": 19
    },
    {
      "time": 1739318400,
      "open": 758.4,
      "high": 788.34,
      "low": 758.4,
      "close": 759.15,
      "volume": 42
    },
    {
      "time": 1739404800,
      "open": 787.84,
      "high": 787.84,
      "low": 708.51,
      "close": 726.32,
      "volume": 489
    },
    {
      "time": 1739491200,
      "open": 776.36,
      "high": 778.66,
      "low": 728.86,
      "close": 744.93,
      "volume": 472
    },
    {
      "time": 1739750400,
      "open": 730.06,
      "high": 748.22,
      "low": 698.73,
      "close": 712.4,
      "volume": 305
    },
    {
      "time": 1739836800,
      "open": 742.98,
      "high": 742.98,
      "low": 680.57,
      "close": 737.75,
      "volume": 181
    },
    {
      "time": 1739923200,
      "open": 753.41,
      "high": 753.41,
      "low": 692.54,
      "close": 737.45,
      "volume": 37
    },
    {
      "time": 1740009600,
      "open": 708.51,
      "high": 737.45,
      "low": 708.51,
      "close": 737.45,
      "volume": 3
    },
    {
      "time": 1740096000,
      "open": 737.45,
      "high": 737.45,
      "low": 723.48,
      "close": 723.48,
      "volume": 89
    },
    {
      "time": 1740441600,
      "open": 723.48,
      "high": 747.42,
      "low": 723.48,
      "close": 740.44,
      "volume": 5
    },
    {
      "time": 1740614400,
      "open": 744.43,
      "high": 744.43,
      "low": 744.43,
      "close": 744.43,
      "volume": 35
    },
    {
      "time": 1740700800,
      "open": 725.82,
      "high": 742.24,
      "low": 725.82,
      "close": 735.55,
      "volume": 30
    },
    {
      "time": 1740960000,
      "open": 743.43,
      "high": 763.39,
      "low": 742.24,
      "close": 742.24,
      "volume": 39
    },
    {
      "time": 1741046400,
      "open": 738.44,
      "high": 738.44,
      "low": 737.45,
      "close": 737.45,
      "volume": 64
    },
    {
      "time": 1741132800,
      "open": 738.39,
      "high": 738.39,
      "low": 737.2,
      "close": 737.99,
      "volume": 29
    },
    {
      "time": 1741219200,
      "open": 737.99,
      "high": 737.99,
      "low": 737.99,
      "close": 737.99,
      "volume": 8
    },
    {
      "time": 1741305600,
      "open": 731.46,
      "high": 868.17,
      "low": 731.46,
      "close": 736.95,
      "volume": 295
    },
    {
      "time": 1741564800,
      "open": 749.52,
      "high": 750.42,
      "low": 749.42,
      "close": 750.42,
      "volume": 86
    },
    {
      "time": 1741651200,
      "open": 718.59,
      "high": 776.26,
      "low": 718.59,
      "close": 729.16,
      "volume": 29
    },
    {
      "time": 1741737600,
      "open": 729.46,
      "high": 729.46,
      "low": 720.48,
      "close": 720.48,
      "volume": 17
    },
    {
      "time": 1741824000,
      "open": 726.47,
      "high": 726.47,
      "low": 719.48,
      "close": 719.48,
      "volume": 24
    },
    {
      "time": 1742169600,
      "open": 726.47,
      "high": 738.44,
      "low": 699.53,
      "close": 703.62,
      "volume": 84
    },
    {
      "time": 1742256000,
      "open": 748.42,
      "high": 770.38,
      "low": 748.42,
      "close": 751.57,
      "volume": 7
    },
    {
      "time": 1742342400,
      "open": 748.42,
      "high": 751.42,
      "low": 748.42,
      "close": 751.42,
      "volume": 2
    },
    {
      "time": 1742428800,
      "open": 733.45,
      "high": 748.42,
      "low": 706.51,
      "close": 716.49,
      "volume": 244
    },
    {
      "time": 1742515200,
      "open": 748.42,
      "high": 748.42,
      "low": 729.46,
      "close": 748.42,
      "volume": 23
    },
    {
      "time": 1742774400,
      "open": 722.03,
      "high": 722.03,
      "low": 722.03,
      "close": 722.03,
      "volume": 9
    },
    {
      "time": 1742860800,
      "open": 724.32,
      "high": 783.35,
      "low": 724.32,
      "close": 734.2,
      "volume": 66
    },
    {
      "time": 1742947200,
      "open": 723.53,
      "high": 756.41,
      "low": 713.4,
      "close": 731.36,
      "volume": 296
    },
    {
      "time": 1743033600,
      "open": 731.36,
      "high": 731.36,
      "low": 731.36,
      "close": 731.36,
      "volume": 11
    },
    {
      "time": 1743120000,
      "open": 757.25,
      "high": 757.25,
      "low": 723.48,
      "close": 727.02,
      "volume": 52
    },
    {
      "time": 1743465600,
      "open": 763.39,
      "high": 763.39,
      "low": 758.4,
      "close": 758.4,
      "volume": 18
    },
    {
      "time": 1743638400,
      "open": 758.35,
      "high": 773.32,
      "low": 739.34,
      "close": 768.33,
      "volume": 145
    },
    {
      "time": 1743724800,
      "open": 768.33,
      "high": 772.12,
      "low": 719.48,
      "close": 719.53,
      "volume": 13
    },
    {
      "time": 1743984000,
      "open": 719.48,
      "high": 719.48,
      "low": 719.48,
      "close": 719.48,
      "volume": 5
    },
    {
      "time": 1744070400,
      "open": 723.48,
      "high": 768.38,
      "low": 718.49,
      "close": 753.41,
      "volume": 142
    },
    {
      "time": 1744156800,
      "open": 766.38,
      "high": 772.77,
      "low": 766.38,
      "close": 769.33,
      "volume": 41
    },
    {
      "time": 1744329600,
      "open": 768.38,
      "high": 769.33,
      "low": 768.38,
      "close": 769.08,
      "volume": 72
    },
    {
      "time": 1744675200,
      "open": 787.64,
      "high": 787.64,
      "low": 718.49,
      "close": 731.61,
      "volume": 250
    },
    {
      "time": 1744761600,
      "open": 724.97,
      "high": 770.33,
      "low": 724.97,
      "close": 754.26,
      "volume": 384
    },
    {
      "time": 1744848000,
      "open": 753.91,
      "high": 773.37,
      "low": 735.65,
      "close": 763.19,
      "volume": 204
    },
    {
      "time": 1745193600,
      "open": 798.27,
      "high": 798.27,
      "low": 730.46,
      "close": 743.08,
      "volume": 57
    },
    {
      "time": 1745366400,
      "open": 723.62,
      "high": 771.07,
      "low": 718.49,
      "close": 742.53,
      "volume": 454
    },
    {
      "time": 1745452800,
      "open": 742.44,
      "high": 742.53,
      "low": 742.44,
      "close": 742.53,
      "volume": 105
    },
    {
      "time": 1745798400,
      "open": 738.24,
      "high": 738.24,
      "low": 709.6,
      "close": 723.38,
      "volume": 51
    },
    {
      "time": 1745884800,
      "open": 723.38,
      "high": 728.46,
      "low": 708.51,
      "close": 708.51,
      "volume": 58
    },
    {
      "time": 1745971200,
      "open": 771.37,
      "high": 771.37,
      "low": 686.55,
      "close": 710.4,
      "volume": 640
    },
    {
      "time": 1746144000,
      "open": 728.46,
      "high": 748.37,
      "low": 699.58,
      "close": 733.45,
      "volume": 117
    },
    {
      "time": 1746403200,
      "open": 718.49,
      "high": 747.42,
      "low": 718.49,
      "close": 746.43,
      "volume": 64
    },
    {
      "time": 1746489600,
      "open": 719.53,
      "high": 743.38,
      "low": 719.53,
      "close": 723.48,
      "volume": 19
    },
    {
      "time": 1746576000,
      "open": 709.5,
      "high": 713.5,
      "low": 698.53,
      "close": 700.42,
      "volume": 61
    },
    {
      "time": 1746662400,
      "open": 745.43,
      "high": 746.38,
      "low": 686.55,
      "close": 712.5,
      "volume": 129
    },
    {
      "time": 1746748800,
      "open": 698.53,
      "high": 698.53,
      "low": 678.57,
      "close": 697.18,
      "volume": 15
    },
    {
      "time": 1747008000,
      "open": 707.16,
      "high": 722.78,
      "low": 706.51,
      "close": 708.56,
      "volume": 14
    },
    {
      "time": 1747094400,
      "open": 738.44,
      "high": 738.44,
      "low": 731.41,
      "close": 731.46,
      "volume": 9
    },
    {
      "time": 1747180800,
      "open": 702.77,
      "high": 744.43,
      "low": 702.77,
      "close": 728.46,
      "volume": 77
    },
    {
      "time": 1747267200,
      "open": 728.46,
      "high": 748.42,
      "low": 709.55,
      "close": 721.98,
      "volume": 98
    },
    {
      "time": 1747353600,
      "open": 754.41,
      "high": 754.41,
      "low": 743.43,
      "close": 744.03,
      "volume": 73
    },
    {
      "time": 1747612800,
      "open": 744.03,
      "high": 763.19,
      "low": 709.6,
      "close": 715.54,
      "volume": 69
    },
    {
      "time": 1747699200,
      "open": 768.33,
      "high": 775.96,
      "low": 719.48,
      "close": 731.01,
      "volume": 95
    },
    {
      "time": 1747785600,
      "open": 748.42,
      "high": 768.38,
      "low": 731.46,
      "close": 731.46,
      "volume": 216
    },
    {
      "time": 1747872000,
      "open": 731.46,
      "high": 764.39,
      "low": 731.46,
      "close": 761.89,
      "volume": 190
    },
    {
      "time": 1747958400,
      "open": 768.38,
      "high": 768.38,
      "low": 766.33,
      "close": 768.28,
      "volume": 84
    },
    {
      "time": 1748390400,
      "open": 769.33,
      "high": 783.35,
      "low": 739.64,
      "close": 768.78,
      "volume": 627
    },
    {
      "time": 1748476800,
      "open": 781.75,
      "high": 781.75,
      "low": 728.86,
      "close": 735.15,
      "volume": 289
    },
    {
      "time": 1748563200,
      "open": 781.35,
      "high": 791.03,
      "low": 735.15,
      "close": 735.15,
      "volume": 31
    },
    {
      "time": 1748822400,
      "open": 735.15,
      "high": 766.38,
      "low": 727.47,
      "close": 737.2,
      "volume": 130
    },
    {
      "time": 1748908800,
      "open": 748.42,
      "high": 748.42,
      "low": 720.48,
      "close": 720.73,
      "volume": 22
    },
    {
      "time": 1748995200,
      "open": 770.03,
      "high": 770.03,
      "low": 721.98,
      "close": 730.86,
      "volume": 86
    },
    {
      "time": 1749081600,
      "open": 730.86,
      "high": 748.37,
      "low": 715.54,
      "close": 716.29,
      "volume": 42
    },
    {
      "time": 1749168000,
      "open": 767.33,
      "high": 767.33,
      "low": 710.0,
      "close": 717.39,
      "volume": 41
    },
    {
      "time": 1749427200,
      "open": 748.42,
      "high": 758.4,
      "low": 728.46,
      "close": 758.4,
      "volume": 131
    },
    {
      "time": 1749513600,
      "open": 756.41,
      "high": 756.41,
      "low": 729.46,
      "close": 751.57,
      "volume": 72
    },
    {
      "time": 1749600000,
      "open": 747.82,
      "high": 747.82,
      "low": 710.5,
      "close": 729.76,
      "volume": 179
    },
    {
      "time": 1749686400,
      "open": 747.42,
      "high": 747.42,
      "low": 710.65,
      "close": 710.65,
      "volume": 14
    },
    {
      "time": 1749772800,
      "open": 756.26,
      "high": 767.38,
      "low": 716.49,
      "close": 728.61,
      "volume": 293
    },
    {
      "time": 1750032000,
      "open": 765.29,
      "high": 765.39,
      "low": 720.98,
      "close": 760.75,
      "volume": 411
    },
    {
      "time": 1750118400,
      "open": 760.75,
      "high": 760.75,
      "low": 723.97,
      "close": 732.86,
      "volume": 88
    },
    {
      "time": 1750204800,
      "open": 730.46,
      "high": 740.44,
      "low": 718.59,
      "close": 726.02,
      "volume": 154
    },
    {
      "time": 1750291200,
      "open": 761.4,
      "high": 761.4,
      "low": 728.46,
      "close": 728.46,
      "volume": 39
    },
    {
      "time": 1750377600,
      "open": 752.36,
      "high": 752.36,
      "low": 731.46,
      "close": 733.45,
      "volume": 36
    },
    {
      "time": 1750636800,
      "open": 758.35,
      "high": 758.35,
      "low": 727.47,
      "close": 738.44,
      "volume": 23
    },
    {
      "time": 1750723200,
      "open": 734.75,
      "high": 734.75,
      "low": 718.49,
      "close": 720.13,
      "volume": 14
    },
    {
      "time": 1750809600,
      "open": 720.18,
      "high": 748.32,
      "low": 719.48,
      "close": 721.73,
      "volume": 14
    },
    {
      "time": 1750896000,
      "open": 721.98,
      "high": 764.39,
      "low": 721.98,
      "close": 738.44,
      "volume": 52
    },
    {
      "time": 1750982400,
      "open": 738.44,
      "high": 738.44,
      "low": 738.44,
      "close": 738.44,
      "volume": 1
    },
    {
      "time": 1751241600,
      "open": 699.63,
      "high": 752.41,
      "low": 699.63,
      "close": 746.28,
      "volume": 191
    },
    {
      "time": 1751328000,
      "open": 742.58,
      "high": 742.58,
      "low": 732.46,
      "close": 732.46,
      "volume": 8
    },
    {
      "time": 1751414400,
      "open": 747.13,
      "high": 747.13,
      "low": 743.33,
      "close": 743.33,
      "volume": 5
    },
    {
      "time": 1751500800,
      "open": 760.3,
      "high": 760.3,
      "low": 739.44,
      "close": 753.11,
      "volume": 153
    },
    {
      "time": 1751587200,
      "open": 764.39,
      "high": 764.39,
      "low": 738.49,
      "close": 743.48,
      "volume": 43
    },
    {
      "time": 1751846400,
      "open": 743.48,
      "high": 764.39,
      "low": 729.86,
      "close": 764.39,
      "volume": 32
    },
    {
      "time": 1751932800,
      "open": 764.39,
      "high": 764.39,
      "low": 750.92,
      "close": 750.92,
      "volume": 31
    },
    {
      "time": 1752019200,
      "open": 750.82,
      "high": 750.82,
      "low": 750.82,
      "close": 750.82,
      "volume": 3
    },
    {
      "time": 1752105600,
      "open": 733.45,
      "high": 750.82,
      "low": 733.45,
      "close": 750.82,
      "volume": 23
    },
    {
      "time": 1752192000,
      "open": 750.52,
      "high": 753.41,
      "low": 721.68,
      "close": 753.41,
      "volume": 209
    },
    {
      "time": 1752451200,
      "open": 753.41,
      "high": 753.41,
      "low": 730.91,
      "close": 731.46,
      "volume": 14
    },
    {
      "time": 1752537600,
      "open": 731.46,
      "high": 738.44,
      "low": 719.48,
      "close": 738.44,
      "volume": 77
    },
    {
      "time": 1752624000,
      "open": 742.14,
      "high": 765.24,
      "low": 742.14,
      "close": 742.14,
      "volume": 86
    },
    {
      "time": 1752710400,
      "open": 770.38,
      "high": 770.38,
      "low": 728.46,
      "close": 751.92,
      "volume": 2027
    },
    {
      "time": 1752796800,
      "open": 749.42,
      "high": 749.42,
      "low": 749.37,
      "close": 749.42,
      "volume": 7
    },
    {
      "time": 1753056000,
      "open": 749.42,
      "high": 768.38,
      "low": 726.97,
      "close": 768.28,
      "volume": 246
    },
    {
      "time": 1753142400,
      "open": 763.39,
      "high": 763.39,
      "low": 748.42,
      "close": 762.39,
      "volume": 123
    },
    {
      "time": 1753315200,
      "open": 733.6,
      "high": 753.36,
      "low": 733.6,
      "close": 753.31,
      "volume": 104
    },
    {
      "time": 1753401600,
      "open": 749.42,
      "high": 763.34,
      "low": 738.44,
      "close": 751.42,
      "volume": 182
    },
    {
      "time": 1753747200,
      "open": 752.41,
      "high": 752.41,
      "low": 752.41,
      "close": 752.41,
      "volume": 1
    },
    {
      "time": 1753833600,
      "open": 751.42,
      "high": 768.38,
      "low": 718.49,
      "close": 751.52,
      "volume": 152
    },
    {
      "time": 1753920000,
      "open": 751.42,
      "high": 751.42,
      "low": 724.52,
      "close": 738.44,
      "volume": 73
    },
    {
      "time": 1754006400,
      "open": 738.44,
      "high": 738.44,
      "low": 726.97,
      "close": 728.41,
      "volume": 33
    },
    {
      "time": 1754265600,
      "open": 749.42,
      "high": 749.42,
      "low": 748.42,
      "close": 749.37,
      "volume": 6
    },
    {
      "time": 1754352000,
      "open": 719.43,
      "high": 753.31,
      "low": 699.53,
      "close": 724.02,
      "volume": 135
    },
    {
      "time": 1754438400,
      "open": 724.02,
      "high": 749.42,
      "low": 724.02,
      "close": 738.59,
      "volume": 33
    },
    {
      "time": 1754524800,
      "open": 748.17,
      "high": 748.17,
      "low": 739.44,
      "close": 739.44,
      "volume": 22
    },
    {
      "time": 1754611200,
      "open": 713.5,
      "high": 755.26,
      "low": 710.5,
      "close": 748.42,
      "volume": 11
    },
    {
      "time": 1754870400,
      "open": 748.42,
      "high": 748.42,
      "low": 728.46,
      "close": 728.46,
      "volume": 18
    },
    {
      "time": 1754956800,
      "open": 747.92,
      "high": 747.92,
      "low": 728.46,
      "close": 746.43,
      "volume": 39
    },
    {
      "time": 1755043200,
      "open": 766.38,
      "high": 766.38,
      "low": 745.43,
      "close": 745.93,
      "volume": 33
    },
    {
      "time": 1755129600,
      "open": 746.43,
      "high": 746.43,
      "low": 745.43,
      "close": 745.43,
      "volume": 12
    },
    {
      "time": 1755475200,
      "open": 628.67,
      "high": 745.38,
      "low": 628.67,
      "close": 711.25,
      "volume": 28
    },
    {
      "time": 1755561600,
      "open": 746.43,
      "high": 746.43,
      "low": 745.08,
      "close": 745.08,
      "volume": 4
    },
    {
      "time": 1755648000,
      "open": 730.21,
      "high": 743.43,
      "low": 730.21,
      "close": 743.43,
      "volume": 25
    },
    {
      "time": 1755734400,
      "open": 718.49,
      "high": 740.84,
      "low": 718.49,
      "close": 738.64,
      "volume": 18
    },
    {
      "time": 1755820800,
      "open": 736.45,
      "high": 736.45,
      "low": 736.45,
      "close": 736.45,
      "volume": 2
    },
    {
      "time": 1756080000,
      "open": 743.43,
      "high": 743.43,
      "low": 708.51,
      "close": 708.51,
      "volume": 12
    },
    {
      "time": 1756166400,
      "open": 738.44,
      "high": 738.44,
      "low": 714.49,
      "close": 718.49,
      "volume": 18
    },
    {
      "time": 1756339200,
      "open": 718.49,
      "high": 742.44,
      "low": 680.67,
      "close": 714.94,
      "volume": 74
    },
    {
      "time": 1756425600,
      "open": 699.58,
      "high": 728.46,
      "low": 699.58,
      "close": 707.06,
      "volume": 7
    },
    {
      "time": 1756684800,
      "open": 756.36,
      "high": 756.36,
      "low": 733.45,
      "close": 733.45,
      "volume": 7
    },
    {
      "time": 1756771200,
      "open": 733.45,
      "high": 733.45,
      "low": 729.96,
      "close": 730.46,
      "volume": 153
    },
    {
      "time": 1756857600,
      "open": 730.46,
      "high": 738.44,
      "low": 700.52,
      "close": 734.75,
      "volume": 29
    },
    {
      "time": 1756944000,
      "open": 746.43,
      "high": 746.43,
      "low": 735.45,
      "close": 735.45,
      "volume": 3
    },
    {
      "time": 1757030400,
      "open": 701.07,
      "high": 752.36,
      "low": 701.07,
      "close": 728.46,
      "volume": 9
    },
    {
      "time": 1757289600,
      "open": 727.47,
      "high": 727.82,
      "low": 727.47,
      "close": 727.82,
      "volume": 3
    },
    {
      "time": 1757376000,
      "open": 727.82,
      "high": 738.44,
      "low": 724.22,
      "close": 738.44,
      "volume": 26
    },
    {
      "time": 1757462400,
      "open": 738.44,
      "high": 738.44,
      "low": 738.44,
      "close": 738.44,
      "volume": 1
    },
    {
      "time": 1757548800,
      "open": 734.75,
      "high": 743.43,
      "low": 733.45,
      "close": 742.29,
      "volume": 107
    },
    {
      "time": 1757635200,
      "open": 741.44,
      "high": 741.44,
      "low": 741.44,
      "close": 741.44,
      "volume": 1
    },
    {
      "time": 1757894400,
      "open": 741.44,
      "high": 745.43,
      "low": 701.52,
      "close": 721.73,
      "volume": 171
    },
    {
      "time": 1757980800,
      "open": 744.43,
      "high": 744.43,
      "low": 709.6,
      "close": 709.6,
      "volume": 12
    },
    {
      "time": 1758067200,
      "open": 742.39,
      "high": 742.39,
      "low": 709.6,
      "close": 713.75,
      "volume": 26
    },
    {
      "time": 1758153600,
      "open": 743.43,
      "high": 743.43,
      "low": 704.52,
      "close": 704.91,
      "volume": 28
    },
    {
      "time": 1758240000,
      "open": 733.45,
      "high": 733.45,
      "low": 711.5,
      "close": 711.7,
      "volume": 11
    },
    {
      "time": 1758499200,
      "open": 733.5,
      "high": 735.0,
      "low": 719.0,
      "close": 719.0,
      "volume": 57
    },
    {
      "time": 1758585600,
      "open": 722.55,
      "high": 745.0,
      "low": 722.55,
      "close": 735.0,
      "volume": 44
    },
    {
      "time": 1758672000,
      "open": 735.0,
      "high": 744.9,
      "low": 706.6,
      "close": 736.6,
      "volume": 117
    },
    {
      "time": 1758758400,
      "open": 713.05,
      "high": 714.0,
      "low": 713.05,
      "close": 714.0,
      "volume": 18
    },
    {
      "time": 1759104000,
      "open": 706.45,
      "high": 739.45,
      "low": 706.45,
      "close": 719.0,
      "volume": 60
    },
    {
      "time": 1759190400,
      "open": 738.0,
      "high": 740.0,
      "low": 738.0,
      "close": 740.0,
      "volume": 51
    },
    {
      "time": 1759449600,
      "open": 702.0,
      "high": 738.9,
      "low": 702.0,
      "close": 716.65,
      "volume": 115
    },
    {
      "time": 1759708800,
      "open": 707.1,
      "high": 720.0,
      "low": 700.0,
      "close": 720.0,
      "volume": 10
    },
    {
      "time": 1759795200,
      "open": 720.0,
      "high": 720.0,
      "low": 710.0,
      "close": 720.0,
      "volume": 20
    },
    {
      "time": 1759881600,
      "open": 703.0,
      "high": 731.0,
      "low": 703.0,
      "close": 731.0,
      "volume": 6
    },
    {
      "time": 1759968000,
      "open": 731.0,
      "high": 736.0,
      "low": 707.0,
      "close": 735.0,
      "volume": 53
    },
    {
      "time": 1760054400,
      "open": 740.0,
      "high": 750.0,
      "low": 740.0,
      "close": 744.0,
      "volume": 47
    },
    {
      "time": 1760313600,
      "open": 715.0,
      "high": 763.0,
      "low": 711.2,
      "close": 719.35,
      "volume": 45
    },
    {
      "time": 1760400000,
      "open": 720.0,
      "high": 754.0,
      "low": 712.0,
      "close": 717.3,
      "volume": 27
    },
    {
      "time": 1760572800,
      "open": 705.1,
      "high": 749.9,
      "low": 705.1,
      "close": 741.55,
      "volume": 43
    },
    {
      "time": 1760918400,
      "open": 726.75,
      "high": 740.0,
      "low": 715.0,
      "close": 720.15,
      "volume": 57
    },
    {
      "time": 1761004800,
      "open": 711.0,
      "high": 712.5,
      "low": 711.0,
      "close": 712.4,
      "volume": 7
    },
    {
      "time": 1761177600,
      "open": 730.0,
      "high": 744.95,
      "low": 712.0,
      "close": 713.2,
      "volume": 144
    },
    {
      "time": 1761264000,
      "open": 726.0,
      "high": 726.0,
      "low": 712.0,
      "close": 712.8,
      "volume": 50
    },
    {
      "time": 1761523200,
      "open": 712.8,
      "high": 712.8,
      "low": 712.8,
      "close": 712.8,
      "volume": 2
    },
    {
      "time": 1761609600,
      "open": 712.8,
      "high": 712.8,
      "low": 691.45,
      "close": 691.45,
      "volume": 51
    },
    {
      "time": 1761696000,
      "open": 724.4,
      "high": 724.4,
      "low": 710.0,
      "close": 710.55,
      "volume": 21
    },
    {
      "time": 1761782400,
      "open": 700.0,
      "high": 710.55,
      "low": 700.0,
      "close": 710.55,
      "volume": 58
    },
    {
      "time": 1761868800,
      "open": 739.0,
      "high": 739.0,
      "low": 705.0,
      "close": 719.0,
      "volume": 7
    },
    {
      "time": 1762128000,
      "open": 738.0,
      "high": 738.0,
      "low": 718.0,
      "close": 718.0,
      "volume": 3
    },
    {
      "time": 1762214400,
      "open": 727.0,
      "high": 727.0,
      "low": 710.0,
      "close": 717.0,
      "volume": 5
    },
    {
      "time": 1762387200,
      "open": 716.9,
      "high": 716.9,
      "low": 707.5,
      "close": 712.5,
      "volume": 52
    },
    {
      "time": 1762473600,
      "open": 712.5,
      "high": 712.5,
      "low": 676.9,
      "close": 676.9,
      "volume": 787
    },
    {
      "time": 1762732800,
      "open": 680.0,
      "high": 710.0,
      "low": 680.0,
      "close": 706.2,
      "volume": 59
    },
    {
      "time": 1762819200,
      "open": 720.35,
      "high": 720.35,
      "low": 720.35,
      "close": 720.35,
      "volume": 1
    },
    {
      "time": 1762905600,
      "open": 720.35,
      "high": 720.35,
      "low": 720.35,
      "close": 720.35,
      "volume": 13
    },
    {
      "time": 1762992000,
      "open": 685.0,
      "high": 685.0,
      "low": 685.0,
      "close": 685.0,
      "volume": 6
    },
    {
      "time": 1763078400,
      "open": 712.0,
      "high": 712.0,
      "low": 695.0,
      "close": 695.0,
      "volume": 26
    },
    {
      "time": 1763337600,
      "open": 691.55,
      "high": 729.75,
      "low": 691.55,
      "close": 729.75,
      "volume": 935
    },
    {
      "time": 1763424000,
      "open": 729.75,
      "high": 757.0,
      "low": 729.75,
      "close": 739.0,
      "volume": 110
    },
    {
      "time": 1763510400,
      "open": 703.0,
      "high": 749.9,
      "low": 703.0,
      "close": 749.9,
      "volume": 33
    },
    {
      "time": 1763596800,
      "open": 749.75,
      "high": 749.75,
      "low": 713.15,
      "close": 731.45,
      "volume": 4
    },
    {
      "time": 1763683200,
      "open": 713.5,
      "high": 713.5,
      "low": 695.0,
      "close": 713.5,
      "volume": 14
    },
    {
      "time": 1764201600,
      "open": 682.0,
      "high": 709.0,
      "low": 682.0,
      "close": 709.0,
      "volume": 113
    },
    {
      "time": 1764288000,
      "open": 729.0,
      "high": 729.0,
      "low": 719.0,
      "close": 719.0,
      "volume": 2
    },
    {
      "time": 1764547200,
      "open": 728.9,
      "high": 728.9,
      "low": 728.0,
      "close": 728.0,
      "volume": 4
    },
    {
      "time": 1764633600,
      "open": 730.0,
      "high": 730.0,
      "low": 692.0,
      "close": 692.0,
      "volume": 306
    },
    {
      "time": 1764720000,
      "open": 693.0,
      "high": 725.0,
      "low": 693.0,
      "close": 710.0,
      "volume": 95
    },
    {
      "time": 1764892800,
      "open": 726.0,
      "high": 726.0,
      "low": 670.0,
      "close": 687.6,
      "volume": 819
    },
    {
      "time": 1765152000,
      "open": 697.6,
      "high": 697.6,
      "low": 610.0,
      "close": 646.4,
      "volume": 488
    },
    {
      "time": 1765238400,
      "open": 677.8,
      "high": 688.0,
      "low": 655.0,
      "close": 675.25,
      "volume": 510
    },
    {
      "time": 1765324800,
      "open": 675.0,
      "high": 675.0,
      "low": 675.0,
      "close": 675.0,
      "volume": 3
    },
    {
      "time": 1765411200,
      "open": 632.05,
      "high": 683.9,
      "low": 632.05,
      "close": 636.2,
      "volume": 19
    },
    {
      "time": 1765497600,
      "open": 682.0,
      "high": 700.0,
      "low": 643.0,
      "close": 698.0,
      "volume": 278
    },
    {
      "time": 1765756800,
      "open": 699.0,
      "high": 699.0,
      "low": 699.0,
      "close": 699.0,
      "volume": 1
    },
    {
      "time": 1765843200,
      "open": 651.05,
      "high": 692.9,
      "low": 651.05,
      "close": 661.25,
      "volume": 79
    },
    {
      "time": 1765929600,
      "open": 625.0,
      "high": 661.65,
      "low": 625.0,
      "close": 632.7,
      "volume": 336
    },
    {
      "time": 1766016000,
      "open": 630.0,
      "high": 649.5,
      "low": 605.0,
      "close": 619.05,
      "volume": 335
    },
    {
      "time": 1766102400,
      "open": 632.1,
      "high": 639.0,
      "low": 631.0,
      "close": 632.45,
      "volume": 256
    },
    {
      "time": 1766361600,
      "open": 640.0,
      "high": 640.0,
      "low": 612.0,
      "close": 630.95,
      "volume": 273
    },
    {
      "time": 1766448000,
      "open": 630.5,
      "high": 630.5,
      "low": 630.5,
      "close": 630.5,
      "volume": 15
    },
    {
      "time": 1766534400,
      "open": 606.0,
      "high": 629.9,
      "low": 605.9,
      "close": 617.7,
      "volume": 172
    },
    {
      "time": 1766707200,
      "open": 624.1,
      "high": 638.0,
      "low": 624.1,
      "close": 638.0,
      "volume": 271
    },
    {
      "time": 1766966400,
      "open": 638.0,
      "high": 638.0,
      "low": 607.15,
      "close": 630.0,
      "volume": 32
    },
    {
      "time": 1767052800,
      "open": 630.0,
      "high": 630.0,
      "low": 610.1,
      "close": 615.75,
      "volume": 70
    },
    {
      "time": 1767139200,
      "open": 629.9,
      "high": 679.9,
      "low": 621.5,
      "close": 669.65,
      "volume": 134
    },
    {
      "time": 1767225600,
      "open": 669.65,
      "high": 687.95,
      "low": 667.0,
      "close": 684.9,
      "volume": 131
    },
    {
      "time": 1767312000,
      "open": 698.95,
      "high": 698.95,
      "low": 658.0,
      "close": 687.1,
      "volume": 78
    },
    {
      "time": 1767571200,
      "open": 687.1,
      "high": 701.0,
      "low": 681.0,
      "close": 681.0,
      "volume": 11
    },
    {
      "time": 1767657600,
      "open": 696.95,
      "high": 696.95,
      "low": 643.05,
      "close": 650.0,
      "volume": 39
    },
    {
      "time": 1767744000,
      "open": 687.0,
      "high": 687.0,
      "low": 650.0,
      "close": 659.5,
      "volume": 19
    },
    {
      "time": 1767830400,
      "open": 690.0,
      "high": 690.0,
      "low": 580.0,
      "close": 582.85,
      "volume": 2417
    },
    {
      "time": 1767916800,
      "open": 625.0,
      "high": 650.0,
      "low": 533.1,
      "close": 579.95,
      "volume": 2535
    },
    {
      "time": 1768176000,
      "open": 624.85,
      "high": 624.85,
      "low": 601.0,
      "close": 614.0,
      "volume": 35
    },
    {
      "time": 1768262400,
      "open": 619.9,
      "high": 619.9,
      "low": 609.0,
      "close": 609.0,
      "volume": 18
    },
    {
      "time": 1768348800,
      "open": 618.0,
      "high": 618.0,
      "low": 600.0,
      "close": 606.1,
      "volume": 28
    },
    {
      "time": 1768521600,
      "open": 606.1,
      "high": 617.9,
      "low": 585.1,
      "close": 587.55,
      "volume": 94
    },
    {
      "time": 1768780800,
      "open": 613.9,
      "high": 614.0,
      "low": 612.9,
      "close": 613.8,
      "volume": 102
    },
    {
      "time": 1768867200,
      "open": 587.0,
      "high": 611.95,
      "low": 587.0,
      "close": 599.75,
      "volume": 5
    },
    {
      "time": 1768953600,
      "open": 599.75,
      "high": 600.0,
      "low": 599.75,
      "close": 600.0,
      "volume": 503
    },
    {
      "time": 1769040000,
      "open": 591.05,
      "high": 617.9,
      "low": 590.0,
      "close": 591.8,
      "volume": 13
    },
    {
      "time": 1769126400,
      "open": 617.9,
      "high": 617.9,
      "low": 609.0,
      "close": 609.0,
      "volume": 13
    },
    {
      "time": 1769472000,
      "open": 564.0,
      "high": 616.0,
      "low": 564.0,
      "close": 582.65,
      "volume": 22
    },
    {
      "time": 1769558400,
      "open": 585.0,
      "high": 609.0,
      "low": 570.2,
      "close": 599.3,
      "volume": 30
    },
    {
      "time": 1769644800,
      "open": 605.25,
      "high": 605.25,
      "low": 605.25,
      "close": 605.25,
      "volume": 1
    },
    {
      "time": 1769731200,
      "open": 605.25,
      "high": 609.0,
      "low": 605.25,
      "close": 609.0,
      "volume": 2
    },
    {
      "time": 1769990400,
      "open": 607.9,
      "high": 607.9,
      "low": 601.0,
      "close": 605.9,
      "volume": 15
    },
    {
      "time": 1770076800,
      "open": 615.0,
      "high": 625.0,
      "low": 580.0,
      "close": 600.0,
      "volume": 286
    },
    {
      "time": 1770163200,
      "open": 619.0,
      "high": 625.0,
      "low": 612.0,
      "close": 625.0,
      "volume": 21
    },
    {
      "time": 1770336000,
      "open": 650.0,
      "high": 650.0,
      "low": 601.05,
      "close": 639.85,
      "volume": 3
    },
    {
      "time": 1770595200,
      "open": 649.4,
      "high": 649.4,
      "low": 630.25,
      "close": 633.0,
      "volume": 91
    },
    {
      "time": 1770768000,
      "open": 650.0,
      "high": 650.0,
      "low": 634.0,
      "close": 641.3,
      "volume": 45
    },
    {
      "time": 1770854400,
      "open": 636.0,
      "high": 689.9,
      "low": 610.25,
      "close": 676.6,
      "volume": 120
    },
    {
      "time": 1770940800,
      "open": 692.0,
      "high": 692.0,
      "low": 626.0,
      "close": 677.75,
      "volume": 164
    },
    {
      "time": 1771200000,
      "open": 660.0,
      "high": 674.4,
      "low": 635.15,
      "close": 670.0,
      "volume": 46
    },
    {
      "time": 1771286400,
      "open": 666.0,
      "high": 669.7,
      "low": 666.0,
      "close": 669.7,
      "volume": 41
    },
    {
      "time": 1771372800,
      "open": 669.0,
      "high": 669.0,
      "low": 662.0,
      "close": 668.55,
      "volume": 22
    },
    {
      "time": 1771459200,
      "open": 668.55,
      "high": 668.9,
      "low": 653.0,
      "close": 653.0,
      "volume": 191
    },
    {
      "time": 1771545600,
      "open": 605.05,
      "high": 642.0,
      "low": 605.05,
      "close": 642.0,
      "volume": 24
    },
    {
      "time": 1771804800,
      "open": 642.0,
      "high": 642.0,
      "low": 619.5,
      "close": 641.9,
      "volume": 48
    },
    {
      "time": 1771891200,
      "open": 650.0,
      "high": 650.0,
      "low": 637.0,
      "close": 637.0,
      "volume": 5
    },
    {
      "time": 1771977600,
      "open": 700.0,
      "high": 700.05,
      "low": 625.0,
      "close": 626.1,
      "volume": 325
    },
    {
      "time": 1772064000,
      "open": 628.05,
      "high": 628.05,
      "low": 575.0,
      "close": 618.0,
      "volume": 228
    },
    {
      "time": 1772150400,
      "open": 590.0,
      "high": 620.0,
      "low": 590.0,
      "close": 606.0,
      "volume": 3
    },
    {
      "time": 1772409600,
      "open": 606.0,
      "high": 606.0,
      "low": 585.0,
      "close": 585.0,
      "volume": 16
    },
    {
      "time": 1772582400,
      "open": 585.0,
      "high": 585.0,
      "low": 569.3,
      "close": 571.2,
      "volume": 87
    },
    {
      "time": 1772668800,
      "open": 572.05,
      "high": 581.0,
      "low": 551.0,
      "close": 578.6,
      "volume": 74
    },
    {
      "time": 1772755200,
      "open": 614.6,
      "high": 614.85,
      "low": 614.6,
      "close": 614.85,
      "volume": 72
    },
    {
      "time": 1773014400,
      "open": 619.9,
      "high": 620.0,
      "low": 600.1,
      "close": 600.25,
      "volume": 17
    },
    {
      "time": 1773187200,
      "open": 600.35,
      "high": 600.35,
      "low": 591.0,
      "close": 598.0,
      "volume": 26
    },
    {
      "time": 1773273600,
      "open": 598.0,
      "high": 598.0,
      "low": 586.0,
      "close": 589.0,
      "volume": 102
    },
    {
      "time": 1773360000,
      "open": 589.0,
      "high": 590.0,
      "low": 586.0,
      "close": 586.0,
      "volume": 21
    },
    {
      "time": 1773619200,
      "open": 613.9,
      "high": 613.9,
      "low": 610.0,
      "close": 610.0,
      "volume": 12
    },
    {
      "time": 1773878400,
      "open": 613.85,
      "high": 613.85,
      "low": 580.05,
      "close": 591.2,
      "volume": 24
    },
    {
      "time": 1773964800,
      "open": 609.0,
      "high": 614.0,
      "low": 609.0,
      "close": 612.9,
      "volume": 83
    },
    {
      "time": 1774224000,
      "open": 615.0,
      "high": 629.95,
      "low": 615.0,
      "close": 619.0,
      "volume": 48
    },
    {
      "time": 1774310400,
      "open": 623.0,
      "high": 623.0,
      "low": 555.0,
      "close": 572.8,
      "volume": 48
    },
    {
      "time": 1774396800,
      "open": 610.0,
      "high": 610.0,
      "low": 610.0,
      "close": 610.0,
      "volume": 5
    },
    {
      "time": 1774828800,
      "open": 610.0,
      "high": 610.0,
      "low": 610.0,
      "close": 610.0,
      "volume": 1
    }
  ]
}