{
  "cache_version": 4,
  "generated_at": "2026-04-01T05:45:16.986404+00:00",
  "bars": [
    {
      "time": 1708646400,
      "open": 16.7,
      "high": 18.4,
      "low": 16.7,
      "close": 17.55,
      "volume": 709944444
    },
    {
      "time": 1708905600,
      "open": 17.75,
      "high": 18.1,
      "low": 16.75,
      "close": 16.85,
      "volume": 643618097
    },
    {
      "time": 1708992000,
      "open": 17.05,
      "high": 17.15,
      "low": 15.65,
      "close": 15.85,
      "volume": 737336815
    },
    {
      "time": 1709078400,
      "open": 15.5,
      "high": 16.05,
      "low": 13.5,
      "close": 13.65,
      "volume": 514581283
    },
    {
      "time": 1709164800,
      "open": 13.65,
      "high": 14.05,
      "low": 13.4,
      "close": 13.65,
      "volume": 794570550
    },
    {
      "time": 1709251200,
      "open": 13.9,
      "high": 14.65,
      "low": 13.6,
      "close": 14.2,
      "volume": 696930662
    },
    {
      "time": 1709510400,
      "open": 14.6,
      "high": 14.7,
      "low": 14.1,
      "close": 14.2,
      "volume": 276443611
    },
    {
      "time": 1709596800,
      "open": 14.25,
      "high": 14.75,
      "low": 14.2,
      "close": 14.35,
      "volume": 342317617
    },
    {
      "time": 1709683200,
      "open": 14.35,
      "high": 14.4,
      "low": 13.8,
      "close": 14.1,
      "volume": 380743524
    },
    {
      "time": 1709769600,
      "open": 14.15,
      "high": 14.45,
      "low": 14.1,
      "close": 14.25,
      "volume": 179243860
    },
    {
      "time": 1710115200,
      "open": 14.3,
      "high": 14.35,
      "low": 13.65,
      "close": 13.75,
      "volume": 198993553
    },
    {
      "time": 1710201600,
      "open": 13.8,
      "high": 13.9,
      "low": 13.45,
      "close": 13.7,
      "volume": 308460037
    },
    {
      "time": 1710288000,
      "open": 13.7,
      "high": 13.85,
      "low": 11.75,
      "close": 12.4,
      "volume": 641919311
    },
    {
      "time": 1710374400,
      "open": 12.4,
      "high": 13.25,
      "low": 12.25,
      "close": 13.1,
      "volume": 424512161
    },
    {
      "time": 1710460800,
      "open": 13.15,
      "high": 13.3,
      "low": 12.75,
      "close": 13.15,
      "volume": 315084932
    },
    {
      "time": 1710720000,
      "open": 13.25,
      "high": 13.35,
      "low": 13.0,
      "close": 13.15,
      "volume": 186892003
    },
    {
      "time": 1710806400,
      "open": 13.1,
      "high": 13.35,
      "low": 12.75,
      "close": 12.85,
      "volume": 241083537
    },
    {
      "time": 1710892800,
      "open": 12.8,
      "high": 12.9,
      "low": 12.4,
      "close": 12.75,
      "volume": 273287247
    },
    {
      "time": 1710979200,
      "open": 12.85,
      "high": 13.05,
      "low": 12.75,
      "close": 12.8,
      "volume": 156394003
    },
    {
      "time": 1711065600,
      "open": 12.8,
      "high": 13.6,
      "low": 12.75,
      "close": 13.3,
      "volume": 468500920
    },
    {
      "time": 1711411200,
      "open": 13.4,
      "high": 13.5,
      "low": 13.15,
      "close": 13.3,
      "volume": 277730489
    },
    {
      "time": 1711497600,
      "open": 13.3,
      "high": 13.6,
      "low": 13.25,
      "close": 13.3,
      "volume": 244147174
    },
    {
      "time": 1711584000,
      "open": 13.3,
      "high": 13.55,
      "low": 13.15,
      "close": 13.25,
      "volume": 261797107
    },
    {
      "time": 1711929600,
      "open": 13.35,
      "high": 14.25,
      "low": 13.15,
      "close": 14.0,
      "volume": 469724659
    },
    {
      "time": 1712016000,
      "open": 13.95,
      "high": 14.15,
      "low": 13.35,
      "close": 13.45,
      "volume": 372670017
    },
    {
      "time": 1712102400,
      "open": 13.2,
      "high": 14.0,
      "low": 13.15,
      "close": 13.55,
      "volume": 496512224
    },
    {
      "time": 1712188800,
      "open": 14.0,
      "high": 14.1,
      "low": 13.05,
      "close": 13.35,
      "volume": 921811399
    },
    {
      "time": 1712275200,
      "open": 13.35,
      "high": 13.55,
      "low": 12.95,
      "close": 13.3,
      "volume": 690376450
    },
    {
      "time": 1712534400,
      "open": 13.9,
      "high": 13.9,
      "low": 12.9,
      "close": 13.15,
      "volume": 770438882
    },
    {
      "time": 1712620800,
      "open": 13.2,
      "high": 13.35,
      "low": 12.85,
      "close": 12.9,
      "volume": 364108806
    },
    {
      "time": 1712707200,
      "open": 12.8,
      "high": 13.2,
      "low": 12.65,
      "close": 12.95,
      "volume": 512312743
    },
    {
      "time": 1712880000,
      "open": 12.65,
      "high": 13.25,
      "low": 12.2,
      "close": 12.95,
      "volume": 60190289
    },
    {
      "time": 1713139200,
      "open": 13.0,
      "high": 13.4,
      "low": 12.75,
      "close": 13.15,
      "volume": 776597931
    },
    {
      "time": 1713225600,
      "open": 12.85,
      "high": 13.2,
      "low": 12.55,
      "close": 12.95,
      "volume": 144793755
    },
    {
      "time": 1713398400,
      "open": 13.1,
      "high": 13.55,
      "low": 13.1,
      "close": 13.2,
      "volume": 791868513
    },
    {
      "time": 1713484800,
      "open": 12.9,
      "high": 13.3,
      "low": 12.85,
      "close": 12.9,
      "volume": 721586766
    },
    {
      "time": 1713744000,
      "open": 12.4,
      "high": 13.05,
      "low": 12.1,
      "close": 12.9,
      "volume": 608298209
    },
    {
      "time": 1713830400,
      "open": 13.0,
      "high": 14.75,
      "low": 12.95,
      "close": 14.4,
      "volume": 1073741823
    },
    {
      "time": 1713916800,
      "open": 13.75,
      "high": 13.95,
      "low": 13.0,
      "close": 13.1,
      "volume": 560864623
    },
    {
      "time": 1714003200,
      "open": 11.8,
      "high": 14.4,
      "low": 11.8,
      "close": 13.9,
      "volume": 1073741823
    },
    {
      "time": 1714089600,
      "open": 13.65,
      "high": 14.2,
      "low": 12.7,
      "close": 14.0,
      "volume": 1376
    },
    {
      "time": 1714348800,
      "open": 14.0,
      "high": 14.3,
      "low": 13.4,
      "close": 13.45,
      "volume": 254582782
    },
    {
      "time": 1714435200,
      "open": 13.5,
      "high": 13.55,
      "low": 13.15,
      "close": 13.2,
      "volume": 954953718
    },
    {
      "time": 1714608000,
      "open": 13.25,
      "high": 13.5,
      "low": 13.1,
      "close": 13.2,
      "volume": 808543713
    },
    {
      "time": 1714694400,
      "open": 13.3,
      "high": 13.5,
      "low": 13.0,
      "close": 13.2,
      "volume": 844184176
    },
    {
      "time": 1714953600,
      "open": 13.25,
      "high": 13.3,
      "low": 12.75,
      "close": 12.8,
      "volume": 688684063
    },
    {
      "time": 1715040000,
      "open": 12.85,
      "high": 12.9,
      "low": 12.1,
      "close": 12.4,
      "volume": 223623015
    },
    {
      "time": 1715126400,
      "open": 12.45,
      "high": 12.85,
      "low": 12.35,
      "close": 12.7,
      "volume": 637428822
    },
    {
      "time": 1715212800,
      "open": 12.75,
      "high": 13.0,
      "low": 12.6,
      "close": 12.65,
      "volume": 643889725
    },
    {
      "time": 1715299200,
      "open": 12.7,
      "high": 12.8,
      "low": 12.45,
      "close": 12.7,
      "volume": 375478451
    },
    {
      "time": 1715558400,
      "open": 12.6,
      "high": 12.7,
      "low": 12.3,
      "close": 12.6,
      "volume": 357347341
    },
    {
      "time": 1715644800,
      "open": 12.7,
      "high": 13.3,
      "low": 12.65,
      "close": 13.25,
      "volume": 745058401
    },
    {
      "time": 1715731200,
      "open": 13.35,
      "high": 13.4,
      "low": 13.1,
      "close": 13.2,
      "volume": 399412030
    },
    {
      "time": 1715817600,
      "open": 13.25,
      "high": 13.4,
      "low": 12.95,
      "close": 13.15,
      "volume": 455941660
    },
    {
      "time": 1715904000,
      "open": 13.15,
      "high": 13.65,
      "low": 13.05,
      "close": 13.25,
      "volume": 630732734
    },
    {
      "time": 1716249600,
      "open": 13.55,
      "high": 13.75,
      "low": 13.35,
      "close": 13.55,
      "volume": 652179474
    },
    {
      "time": 1716336000,
      "open": 13.65,
      "high": 13.8,
      "low": 13.45,
      "close": 13.5,
      "volume": 363222831
    },
    {
      "time": 1716422400,
      "open": 13.5,
      "high": 14.1,
      "low": 13.45,
      "close": 14.05,
      "volume": 975684695
    },
    {
      "time": 1716508800,
      "open": 14.25,
      "high": 15.7,
      "low": 14.2,
      "close": 15.1,
      "volume": 3973
    },
    {
      "time": 1716768000,
      "open": 15.2,
      "high": 15.45,
      "low": 14.9,
      "close": 15.05,
      "volume": 963234521
    },
    {
      "time": 1716854400,
      "open": 15.05,
      "high": 15.1,
      "low": 14.5,
      "close": 14.55,
      "volume": 668778744
    },
    {
      "time": 1716940800,
      "open": 14.45,
      "high": 14.9,
      "low": 14.4,
      "close": 14.8,
      "volume": 592922488
    },
    {
      "time": 1717027200,
      "open": 14.85,
      "high": 15.05,
      "low": 14.5,
      "close": 14.6,
      "volume": 21529920
    },
    {
      "time": 1717113600,
      "open": 14.75,
      "high": 15.45,
      "low": 14.65,
      "close": 15.25,
      "volume": 839643261
    },
    {
      "time": 1717372800,
      "open": 16.4,
      "high": 16.4,
      "low": 15.65,
      "close": 16.0,
      "volume": 260907611
    },
    {
      "time": 1717459200,
      "open": 15.7,
      "high": 15.7,
      "low": 12.05,
      "close": 13.2,
      "volume": 821
    },
    {
      "time": 1717545600,
      "open": 13.65,
      "high": 15.05,
      "low": 13.3,
      "close": 14.85,
      "volume": 501552249
    },
    {
      "time": 1717632000,
      "open": 15.15,
      "high": 15.4,
      "low": 14.85,
      "close": 15.0,
      "volume": 853275763
    },
    {
      "time": 1717718400,
      "open": 15.05,
      "high": 16.05,
      "low": 14.9,
      "close": 15.85,
      "volume": 177663038
    },
    {
      "time": 1717977600,
      "open": 15.96,
      "high": 16.35,
      "low": 15.76,
      "close": 15.81,
      "volume": 14989971
    },
    {
      "time": 1718064000,
      "open": 15.95,
      "high": 16.32,
      "low": 15.61,
      "close": 16.19,
      "volume": 94572074
    },
    {
      "time": 1718150400,
      "open": 16.3,
      "high": 16.7,
      "low": 16.24,
      "close": 16.43,
      "volume": 1041028161
    },
    {
      "time": 1718236800,
      "open": 16.73,
      "high": 16.74,
      "low": 16.0,
      "close": 16.07,
      "volume": 731987121
    },
    {
      "time": 1718323200,
      "open": 16.3,
      "high": 16.85,
      "low": 16.06,
      "close": 16.73,
      "volume": 27007761
    },
    {
      "time": 1718668800,
      "open": 16.99,
      "high": 17.03,
      "low": 16.48,
      "close": 16.85,
      "volume": 804338492
    },
    {
      "time": 1718755200,
      "open": 17.0,
      "high": 17.39,
      "low": 16.36,
      "close": 16.92,
      "volume": 1564573800
    },
    {
      "time": 1718841600,
      "open": 16.97,
      "high": 16.97,
      "low": 16.45,
      "close": 16.53,
      "volume": 745416817
    },
    {
      "time": 1718928000,
      "open": 16.61,
      "high": 17.28,
      "low": 16.54,
      "close": 17.14,
      "volume": 681222197
    },
    {
      "time": 1719187200,
      "open": 16.99,
      "high": 17.34,
      "low": 16.86,
      "close": 17.26,
      "volume": 946446301
    },
    {
      "time": 1719273600,
      "open": 17.45,
      "high": 17.5,
      "low": 17.15,
      "close": 17.19,
      "volume": 664334923
    },
    {
      "time": 1719360000,
      "open": 17.24,
      "high": 18.47,
      "low": 17.22,
      "close": 18.02,
      "volume": 446331568
    },
    {
      "time": 1719446400,
      "open": 18.25,
      "high": 18.7,
      "low": 18.0,
      "close": 18.52,
      "volume": 449366808
    },
    {
      "time": 1719532800,
      "open": 19.1,
      "high": 19.18,
      "low": 17.55,
      "close": 17.89,
      "volume": 940893249
    },
    {
      "time": 1719792000,
      "open": 17.79,
      "high": 18.06,
      "low": 17.4,
      "close": 17.62,
      "volume": 877984912
    },
    {
      "time": 1719878400,
      "open": 17.7,
      "high": 17.75,
      "low": 16.96,
      "close": 17.02,
      "volume": 826792635
    },
    {
      "time": 1719964800,
      "open": 17.1,
      "high": 17.67,
      "low": 16.91,
      "close": 17.47,
      "volume": 860849573
    },
    {
      "time": 1720051200,
      "open": 17.51,
      "high": 17.74,
      "low": 17.28,
      "close": 17.48,
      "volume": 644674371
    },
    {
      "time": 1720137600,
      "open": 17.44,
      "high": 17.48,
      "low": 17.01,
      "close": 17.09,
      "volume": 492372970
    },
    {
      "time": 1720396800,
      "open": 17.1,
      "high": 17.23,
      "low": 16.5,
      "close": 16.56,
      "volume": 541264689
    },
    {
      "time": 1720483200,
      "open": 16.61,
      "high": 17.03,
      "low": 16.56,
      "close": 16.85,
      "volume": 501290567
    },
    {
      "time": 1720569600,
      "open": 16.97,
      "high": 17.28,
      "low": 16.47,
      "close": 16.64,
      "volume": 466478026
    },
    {
      "time": 1720656000,
      "open": 16.76,
      "high": 16.84,
      "low": 16.52,
      "close": 16.56,
      "volume": 346369340
    },
    {
      "time": 1720742400,
      "open": 16.76,
      "high": 16.83,
      "low": 16.0,
      "close": 16.09,
      "volume": 630743126
    },
    {
      "time": 1721001600,
      "open": 16.1,
      "high": 16.73,
      "low": 15.78,
      "close": 16.68,
      "volume": 544664305
    },
    {
      "time": 1721088000,
      "open": 17.54,
      "high": 17.67,
      "low": 16.67,
      "close": 16.8,
      "volume": 964458628
    },
    {
      "time": 1721260800,
      "open": 16.69,
      "high": 16.69,
      "low": 15.91,
      "close": 16.27,
      "volume": 679246298
    },
    {
      "time": 1721347200,
      "open": 16.37,
      "high": 16.43,
      "low": 15.82,
      "close": 15.87,
      "volume": 368882386
    },
    {
      "time": 1721606400,
      "open": 15.77,
      "high": 16.05,
      "low": 15.65,
      "close": 15.89,
      "volume": 529018766
    },
    {
      "time": 1721692800,
      "open": 15.9,
      "high": 15.91,
      "low": 14.57,
      "close": 15.28,
      "volume": 53671237
    },
    {
      "time": 1721779200,
      "open": 15.3,
      "high": 15.66,
      "low": 15.21,
      "close": 15.58,
      "volume": 453449137
    },
    {
      "time": 1721865600,
      "open": 15.3,
      "high": 15.42,
      "low": 15.03,
      "close": 15.18,
      "volume": 702308285
    },
    {
      "time": 1721952000,
      "open": 15.42,
      "high": 16.14,
      "low": 15.4,
      "close": 15.98,
      "volume": 746610397
    },
    {
      "time": 1722211200,
      "open": 16.0,
      "high": 16.42,
      "low": 15.93,
      "close": 16.05,
      "volume": 505926060
    },
    {
      "time": 1722297600,
      "open": 16.03,
      "high": 16.28,
      "low": 15.99,
      "close": 16.21,
      "volume": 242396205
    },
    {
      "time": 1722384000,
      "open": 16.31,
      "high": 16.52,
      "low": 16.22,
      "close": 16.27,
      "volume": 346265142
    },
    {
      "time": 1722470400,
      "open": 16.36,
      "high": 16.37,
      "low": 15.87,
      "close": 15.99,
      "volume": 362395270
    },
    {
      "time": 1722556800,
      "open": 15.8,
      "high": 16.42,
      "low": 15.75,
      "close": 16.12,
      "volume": 475279605
    },
    {
      "time": 1722816000,
      "open": 15.61,
      "high": 15.81,
      "low": 15.05,
      "close": 15.36,
      "volume": 608655754
    },
    {
      "time": 1722902400,
      "open": 15.7,
      "high": 15.83,
      "low": 15.11,
      "close": 15.17,
      "volume": 327583325
    },
    {
      "time": 1722988800,
      "open": 15.6,
      "high": 15.78,
      "low": 15.37,
      "close": 15.72,
      "volume": 271137134
    },
    {
      "time": 1723075200,
      "open": 15.75,
      "high": 16.25,
      "low": 15.57,
      "close": 15.86,
      "volume": 346746624
    },
    {
      "time": 1723161600,
      "open": 16.3,
      "high": 16.35,
      "low": 16.01,
      "close": 16.1,
      "volume": 276415001
    },
    {
      "time": 1723420800,
      "open": 16.12,
      "high": 16.22,
      "low": 15.82,
      "close": 16.01,
      "volume": 290810714
    },
    {
      "time": 1723507200,
      "open": 16.19,
      "high": 16.19,
      "low": 15.42,
      "close": 15.47,
      "volume": 538387007
    },
    {
      "time": 1723593600,
      "open": 15.63,
      "high": 16.02,
      "low": 15.48,
      "close": 15.79,
      "volume": 392047253
    },
    {
      "time": 1723766400,
      "open": 15.96,
      "high": 16.0,
      "low": 15.67,
      "close": 15.88,
      "volume": 291922661
    },
    {
      "time": 1724025600,
      "open": 15.87,
      "high": 16.04,
      "low": 15.72,
      "close": 15.95,
      "volume": 265264602
    },
    {
      "time": 1724112000,
      "open": 16.06,
      "high": 16.29,
      "low": 15.91,
      "close": 15.94,
      "volume": 309490369
    },
    {
      "time": 1724198400,
      "open": 15.99,
      "high": 16.1,
      "low": 15.86,
      "close": 15.94,
      "volume": 242515086
    },
    {
      "time": 1724284800,
      "open": 15.95,
      "high": 16.29,
      "low": 15.91,
      "close": 16.2,
      "volume": 278652089
    },
    {
      "time": 1724371200,
      "open": 16.28,
      "high": 16.34,
      "low": 15.74,
      "close": 15.82,
      "volume": 369537715
    },
    {
      "time": 1724630400,
      "open": 15.96,
      "high": 15.98,
      "low": 15.62,
      "close": 15.79,
      "volume": 243427186
    },
    {
      "time": 1724716800,
      "open": 15.75,
      "high": 16.18,
      "low": 15.65,
      "close": 16.04,
      "volume": 415465213
    },
    {
      "time": 1724803200,
      "open": 16.05,
      "high": 16.17,
      "low": 15.82,
      "close": 15.97,
      "volume": 401712642
    },
    {
      "time": 1724889600,
      "open": 16.4,
      "high": 16.55,
      "low": 15.97,
      "close": 16.3,
      "volume": 827342035
    },
    {
      "time": 1724976000,
      "open": 16.44,
      "high": 16.44,
      "low": 15.39,
      "close": 15.64,
      "volume": 1131
    },
    {
      "time": 1725235200,
      "open": 15.58,
      "high": 15.58,
      "low": 14.81,
      "close": 15.05,
      "volume": 685959065
    },
    {
      "time": 1725321600,
      "open": 15.1,
      "high": 15.26,
      "low": 15.0,
      "close": 15.11,
      "volume": 272427038
    },
    {
      "time": 1725408000,
      "open": 15.08,
      "high": 15.1,
      "low": 14.77,
      "close": 14.83,
      "volume": 281283093
    },
    {
      "time": 1725494400,
      "open": 14.9,
      "high": 15.22,
      "low": 14.8,
      "close": 15.09,
      "volume": 286740484
    },
    {
      "time": 1725580800,
      "open": 14.74,
      "high": 14.76,
      "low": 12.92,
      "close": 13.35,
      "volume": 827451206
    },
    {
      "time": 1725840000,
      "open": 13.35,
      "high": 13.58,
      "low": 12.98,
      "close": 13.2,
      "volume": 628833307
    },
    {
      "time": 1725926400,
      "open": 13.3,
      "high": 13.73,
      "low": 13.3,
      "close": 13.53,
      "volume": 444283492
    },
    {
      "time": 1726012800,
      "open": 13.74,
      "high": 13.77,
      "low": 13.03,
      "close": 13.14,
      "volume": 358061345
    },
    {
      "time": 1726099200,
      "open": 13.36,
      "high": 13.65,
      "low": 12.83,
      "close": 13.52,
      "volume": 408314409
    },
    {
      "time": 1726185600,
      "open": 13.65,
      "high": 13.66,
      "low": 13.36,
      "close": 13.41,
      "volume": 198209238
    },
    {
      "time": 1726444800,
      "open": 13.5,
      "high": 13.5,
      "low": 13.12,
      "close": 13.24,
      "volume": 261780637
    },
    {
      "time": 1726531200,
      "open": 13.25,
      "high": 13.28,
      "low": 13.07,
      "close": 13.12,
      "volume": 179383176
    },
    {
      "time": 1726617600,
      "open": 13.1,
      "high": 13.16,
      "low": 12.83,
      "close": 12.9,
      "volume": 289385698
    },
    {
      "time": 1726704000,
      "open": 12.99,
      "high": 13.02,
      "low": 10.0,
      "close": 10.38,
      "volume": 997
    },
    {
      "time": 1726790400,
      "open": 10.35,
      "high": 10.58,
      "low": 9.79,
      "close": 10.47,
      "volume": 454680485
    },
    {
      "time": 1727049600,
      "open": 11.27,
      "high": 11.94,
      "low": 10.72,
      "close": 10.82,
      "volume": 608733575
    },
    {
      "time": 1727136000,
      "open": 10.82,
      "high": 10.99,
      "low": 10.52,
      "close": 10.67,
      "volume": 591115783
    },
    {
      "time": 1727222400,
      "open": 10.69,
      "high": 10.73,
      "low": 10.33,
      "close": 10.36,
      "volume": 386280914
    },
    {
      "time": 1727308800,
      "open": 10.39,
      "high": 10.5,
      "low": 10.12,
      "close": 10.38,
      "volume": 947225586
    },
    {
      "time": 1727395200,
      "open": 10.64,
      "high": 10.97,
      "low": 10.5,
      "close": 10.66,
      "volume": 48984351
    },
    {
      "time": 1727654400,
      "open": 10.65,
      "high": 10.68,
      "low": 10.32,
      "close": 10.36,
      "volume": 469780209
    },
    {
      "time": 1727740800,
      "open": 10.35,
      "high": 10.53,
      "low": 10.06,
      "close": 10.17,
      "volume": 372735715
    },
    {
      "time": 1727913600,
      "open": 10.13,
      "high": 10.16,
      "low": 9.81,
      "close": 9.87,
      "volume": 418426001
    },
    {
      "time": 1728000000,
      "open": 9.87,
      "high": 10.06,
      "low": 9.63,
      "close": 9.79,
      "volume": 453013199
    },
    {
      "time": 1728259200,
      "open": 9.79,
      "high": 9.81,
      "low": 8.9,
      "close": 9.16,
      "volume": 699375979
    },
    {
      "time": 1728345600,
      "open": 9.05,
      "high": 9.55,
      "low": 9.03,
      "close": 9.5,
      "volume": 447500823
    },
    {
      "time": 1728432000,
      "open": 9.54,
      "high": 9.58,
      "low": 9.16,
      "close": 9.19,
      "volume": 286231290
    },
    {
      "time": 1728518400,
      "open": 9.21,
      "high": 9.44,
      "low": 9.19,
      "close": 9.31,
      "volume": 274431844
    },
    {
      "time": 1728604800,
      "open": 9.27,
      "high": 9.28,
      "low": 9.08,
      "close": 9.18,
      "volume": 263957905
    },
    {
      "time": 1728864000,
      "open": 9.23,
      "high": 9.23,
      "low": 9.02,
      "close": 9.09,
      "volume": 295768306
    },
    {
      "time": 1728950400,
      "open": 9.11,
      "high": 9.42,
      "low": 9.0,
      "close": 9.12,
      "volume": 307249022
    },
    {
      "time": 1729036800,
      "open": 9.15,
      "high": 9.49,
      "low": 9.11,
      "close": 9.29,
      "volume": 329180888
    },
    {
      "time": 1729123200,
      "open": 9.31,
      "high": 9.39,
      "low": 9.03,
      "close": 9.05,
      "volume": 327847932
    },
    {
      "time": 1729209600,
      "open": 9.05,
      "high": 9.1,
      "low": 8.86,
      "close": 9.02,
      "volume": 273123417
    },
    {
      "time": 1729468800,
      "open": 9.09,
      "high": 9.1,
      "low": 8.42,
      "close": 8.5,
      "volume": 484398463
    },
    {
      "time": 1729555200,
      "open": 8.52,
      "high": 8.73,
      "low": 8.36,
      "close": 8.4,
      "volume": 445613876
    },
    {
      "time": 1729641600,
      "open": 8.33,
      "high": 8.4,
      "low": 8.07,
      "close": 8.25,
      "volume": 487665119
    },
    {
      "time": 1729728000,
      "open": 8.25,
      "high": 8.33,
      "low": 8.1,
      "close": 8.13,
      "volume": 381020269
    },
    {
      "time": 1729814400,
      "open": 8.11,
      "high": 8.11,
      "low": 7.59,
      "close": 7.66,
      "volume": 601382237
    },
    {
      "time": 1730073600,
      "open": 7.78,
      "high": 8.42,
      "low": 7.58,
      "close": 8.25,
      "volume": 687956967
    },
    {
      "time": 1730160000,
      "open": 8.39,
      "high": 8.39,
      "low": 7.88,
      "close": 7.96,
      "volume": 403510334
    },
    {
      "time": 1730246400,
      "open": 7.93,
      "high": 8.04,
      "low": 7.65,
      "close": 7.68,
      "volume": 919784434
    },
    {
      "time": 1730332800,
      "open": 7.74,
      "high": 8.17,
      "low": 7.71,
      "close": 8.12,
      "volume": 647625664
    },
    {
      "time": 1730419200,
      "open": 8.28,
      "high": 8.53,
      "low": 8.23,
      "close": 8.45,
      "volume": 248654298
    },
    {
      "time": 1730678400,
      "open": 8.49,
      "high": 8.49,
      "low": 7.86,
      "close": 7.88,
      "volume": 609725576
    },
    {
      "time": 1730764800,
      "open": 7.88,
      "high": 8.2,
      "low": 7.81,
      "close": 8.14,
      "volume": 555505932
    },
    {
      "time": 1730851200,
      "open": 8.16,
      "high": 8.22,
      "low": 8.01,
      "close": 8.17,
      "volume": 368621189
    },
    {
      "time": 1730937600,
      "open": 8.16,
      "high": 8.29,
      "low": 8.02,
      "close": 8.05,
      "volume": 383925046
    },
    {
      "time": 1731024000,
      "open": 8.03,
      "high": 8.06,
      "low": 7.85,
      "close": 7.88,
      "volume": 311562033
    },
    {
      "time": 1731283200,
      "open": 7.85,
      "high": 7.94,
      "low": 7.72,
      "close": 7.83,
      "volume": 314187467
    },
    {
      "time": 1731369600,
      "open": 7.8,
      "high": 7.95,
      "low": 7.63,
      "close": 7.67,
      "volume": 280320971
    },
    {
      "time": 1731456000,
      "open": 7.66,
      "high": 7.69,
      "low": 7.33,
      "close": 7.36,
      "volume": 424078967
    },
    {
      "time": 1731542400,
      "open": 7.4,
      "high": 7.62,
      "low": 7.32,
      "close": 7.34,
      "volume": 417566075
    },
    {
      "time": 1731888000,
      "open": 7.47,
      "high": 7.53,
      "low": 7.19,
      "close": 7.25,
      "volume": 418915760
    },
    {
      "time": 1731974400,
      "open": 7.25,
      "high": 7.39,
      "low": 7.07,
      "close": 7.1,
      "volume": 338585471
    },
    {
      "time": 1732147200,
      "open": 7.17,
      "high": 7.18,
      "low": 6.81,
      "close": 6.91,
      "volume": 635819080
    },
    {
      "time": 1732233600,
      "open": 6.88,
      "high": 6.91,
      "low": 6.61,
      "close": 6.67,
      "volume": 625748712
    },
    {
      "time": 1732492800,
      "open": 6.81,
      "high": 7.17,
      "low": 6.67,
      "close": 6.97,
      "volume": 876693538
    },
    {
      "time": 1732579200,
      "open": 7.66,
      "high": 8.28,
      "low": 7.45,
      "close": 7.52,
      "volume": 678390868
    },
    {
      "time": 1732665600,
      "open": 7.72,
      "high": 8.49,
      "low": 7.52,
      "close": 8.34,
      "volume": 88788451
    },
    {
      "time": 1732752000,
      "open": 8.45,
      "high": 8.67,
      "low": 8.21,
      "close": 8.36,
      "volume": 1022944207
    },
    {
      "time": 1732838400,
      "open": 8.46,
      "high": 8.48,
      "low": 8.08,
      "close": 8.36,
      "volume": 507412630
    },
    {
      "time": 1733097600,
      "open": 8.25,
      "high": 8.43,
      "low": 8.19,
      "close": 8.28,
      "volume": 341331191
    },
    {
      "time": 1733184000,
      "open": 8.25,
      "high": 8.39,
      "low": 8.19,
      "close": 8.21,
      "volume": 283636669
    },
    {
      "time": 1733270400,
      "open": 8.19,
      "high": 8.63,
      "low": 8.12,
      "close": 8.42,
      "volume": 406959578
    },
    {
      "time": 1733356800,
      "open": 8.79,
      "high": 8.79,
      "low": 8.04,
      "close": 8.08,
      "volume": 920598588
    },
    {
      "time": 1733443200,
      "open": 8.09,
      "high": 8.22,
      "low": 7.97,
      "close": 8.12,
      "volume": 427143967
    },
    {
      "time": 1733702400,
      "open": 8.15,
      "high": 8.27,
      "low": 8.07,
      "close": 8.09,
      "volume": 297577705
    },
    {
      "time": 1733788800,
      "open": 8.3,
      "high": 8.3,
      "low": 8.02,
      "close": 8.08,
      "volume": 363303722
    },
    {
      "time": 1733875200,
      "open": 8.08,
      "high": 8.11,
      "low": 7.99,
      "close": 8.03,
      "volume": 243838311
    },
    {
      "time": 1733961600,
      "open": 8.02,
      "high": 8.03,
      "low": 7.84,
      "close": 7.86,
      "volume": 292784535
    },
    {
      "time": 1734048000,
      "open": 7.82,
      "high": 8.07,
      "low": 7.68,
      "close": 7.99,
      "volume": 489885434
    },
    {
      "time": 1734307200,
      "open": 8.0,
      "high": 8.05,
      "low": 7.96,
      "close": 7.99,
      "volume": 174023331
    },
    {
      "time": 1734393600,
      "open": 7.95,
      "high": 7.99,
      "low": 7.78,
      "close": 7.81,
      "volume": 252380018
    },
    {
      "time": 1734480000,
      "open": 7.81,
      "high": 7.88,
      "low": 7.7,
      "close": 7.79,
      "volume": 351707657
    },
    {
      "time": 1734566400,
      "open": 7.6,
      "high": 7.72,
      "low": 7.56,
      "close": 7.69,
      "volume": 285980002
    },
    {
      "time": 1734652800,
      "open": 7.68,
      "high": 7.76,
      "low": 7.34,
      "close": 7.4,
      "volume": 392779182
    },
    {
      "time": 1734912000,
      "open": 7.4,
      "high": 7.55,
      "low": 7.38,
      "close": 7.47,
      "volume": 290752314
    },
    {
      "time": 1734998400,
      "open": 7.42,
      "high": 7.59,
      "low": 7.35,
      "close": 7.46,
      "volume": 285539029
    },
    {
      "time": 1735171200,
      "open": 7.46,
      "high": 7.67,
      "low": 7.43,
      "close": 7.56,
      "volume": 276382089
    },
    {
      "time": 1735257600,
      "open": 7.55,
      "high": 7.61,
      "low": 7.45,
      "close": 7.47,
      "volume": 181050583
    },
    {
      "time": 1735516800,
      "open": 7.99,
      "high": 7.99,
      "low": 7.61,
      "close": 7.77,
      "volume": 699337628
    },
    {
      "time": 1735603200,
      "open": 7.75,
      "high": 8.07,
      "low": 7.62,
      "close": 7.94,
      "volume": 432275623
    },
    {
      "time": 1735689600,
      "open": 7.96,
      "high": 8.11,
      "low": 7.9,
      "close": 8.01,
      "volume": 318779771
    },
    {
      "time": 1735776000,
      "open": 8.1,
      "high": 8.19,
      "low": 7.91,
      "close": 8.14,
      "volume": 392797911
    },
    {
      "time": 1735862400,
      "open": 8.14,
      "high": 8.4,
      "low": 8.12,
      "close": 8.27,
      "volume": 464150003
    },
    {
      "time": 1736121600,
      "open": 8.29,
      "high": 8.33,
      "low": 7.83,
      "close": 7.88,
      "volume": 438301803
    },
    {
      "time": 1736208000,
      "open": 7.86,
      "high": 8.14,
      "low": 7.86,
      "close": 8.06,
      "volume": 374162457
    },
    {
      "time": 1736294400,
      "open": 8.08,
      "high": 8.1,
      "low": 7.87,
      "close": 7.99,
      "volume": 294651841
    },
    {
      "time": 1736380800,
      "open": 7.98,
      "high": 8.21,
      "low": 7.9,
      "close": 7.92,
      "volume": 338935170
    },
    {
      "time": 1736467200,
      "open": 7.92,
      "high": 7.95,
      "low": 7.67,
      "close": 7.75,
      "volume": 321647638
    },
    {
      "time": 1736726400,
      "open": 7.7,
      "high": 8.08,
      "low": 7.61,
      "close": 7.74,
      "volume": 597616878
    },
    {
      "time": 1736812800,
      "open": 7.8,
      "high": 8.31,
      "low": 7.77,
      "close": 8.25,
      "volume": 563020922
    },
    {
      "time": 1736899200,
      "open": 8.28,
      "high": 9.23,
      "low": 8.27,
      "close": 8.76,
      "volume": 294552007
    },
    {
      "time": 1736985600,
      "open": 8.94,
      "high": 9.06,
      "low": 8.72,
      "close": 8.93,
      "volume": 536382334
    },
    {
      "time": 1737072000,
      "open": 8.9,
      "high": 9.25,
      "low": 8.83,
      "close": 9.11,
      "volume": 485924287
    },
    {
      "time": 1737331200,
      "open": 10.02,
      "high": 10.47,
      "low": 9.78,
      "close": 9.94,
      "volume": 665312492
    },
    {
      "time": 1737417600,
      "open": 9.94,
      "high": 10.0,
      "low": 9.31,
      "close": 9.36,
      "volume": 561246192
    },
    {
      "time": 1737504000,
      "open": 9.4,
      "high": 9.57,
      "low": 9.14,
      "close": 9.51,
      "volume": 358652788
    },
    {
      "time": 1737590400,
      "open": 9.53,
      "high": 9.87,
      "low": 9.33,
      "close": 9.51,
      "volume": 356247545
    },
    {
      "time": 1737676800,
      "open": 9.5,
      "high": 9.67,
      "low": 9.4,
      "close": 9.46,
      "volume": 272054686
    },
    {
      "time": 1737936000,
      "open": 9.3,
      "high": 9.34,
      "low": 8.8,
      "close": 8.89,
      "volume": 319471529
    },
    {
      "time": 1738022400,
      "open": 8.99,
      "high": 9.15,
      "low": 8.78,
      "close": 9.0,
      "volume": 310325356
    },
    {
      "time": 1738108800,
      "open": 9.0,
      "high": 9.06,
      "low": 8.9,
      "close": 8.94,
      "volume": 186423902
    },
    {
      "time": 1738195200,
      "open": 8.86,
      "high": 9.05,
      "low": 8.86,
      "close": 8.99,
      "volume": 255095259
    },
    {
      "time": 1738281600,
      "open": 9.05,
      "high": 9.1,
      "low": 8.88,
      "close": 9.05,
      "volume": 336820197
    },
    {
      "time": 1738368000,
      "open": 9.06,
      "high": 9.93,
      "low": 8.67,
      "close": 9.6,
      "volume": 807081992
    },
    {
      "time": 1738540800,
      "open": 9.21,
      "high": 9.41,
      "low": 9.02,
      "close": 9.07,
      "volume": 384582320
    },
    {
      "time": 1738627200,
      "open": 9.29,
      "high": 9.61,
      "low": 9.09,
      "close": 9.4,
      "volume": 418244166
    },
    {
      "time": 1738713600,
      "open": 9.4,
      "high": 9.7,
      "low": 9.39,
      "close": 9.54,
      "volume": 349183730
    },
    {
      "time": 1738800000,
      "open": 9.66,
      "high": 9.66,
      "low": 9.23,
      "close": 9.27,
      "volume": 223076819
    },
    {
      "time": 1738886400,
      "open": 9.29,
      "high": 9.8,
      "low": 9.27,
      "close": 9.47,
      "volume": 605199609
    },
    {
      "time": 1739145600,
      "open": 9.55,
      "high": 9.55,
      "low": 9.06,
      "close": 9.11,
      "volume": 262161729
    },
    {
      "time": 1739232000,
      "open": 9.11,
      "high": 9.17,
      "low": 8.72,
      "close": 8.82,
      "volume": 258460983
    },
    {
      "time": 1739318400,
      "open": 8.8,
      "high": 8.8,
      "low": 8.1,
      "close": 8.39,
      "volume": 576588022
    },
    {
      "time": 1739404800,
      "open": 8.06,
      "high": 8.99,
      "low": 8.06,
      "close": 8.64,
      "volume": 717308741
    },
    {
      "time": 1739491200,
      "open": 8.76,
      "high": 8.79,
      "low": 8.1,
      "close": 8.21,
      "volume": 497212290
    },
    {
      "time": 1739750400,
      "open": 8.17,
      "high": 8.4,
      "low": 7.98,
      "close": 8.27,
      "volume": 427122426
    },
    {
      "time": 1739836800,
      "open": 8.27,
      "high": 8.35,
      "low": 7.92,
      "close": 8.07,
      "volume": 332529559
    },
    {
      "time": 1739923200,
      "open": 8.03,
      "high": 8.39,
      "low": 7.94,
      "close": 8.3,
      "volume": 299864398
    },
    {
      "time": 1740009600,
      "open": 8.27,
      "high": 8.4,
      "low": 8.18,
      "close": 8.27,
      "volume": 197667113
    },
    {
      "time": 1740096000,
      "open": 8.25,
      "high": 8.34,
      "low": 8.01,
      "close": 8.04,
      "volume": 289642446
    },
    {
      "time": 1740355200,
      "open": 7.98,
      "high": 8.04,
      "low": 7.84,
      "close": 7.92,
      "volume": 265949359
    },
    {
      "time": 1740441600,
      "open": 7.9,
      "high": 8.04,
      "low": 7.88,
      "close": 7.91,
      "volume": 202132636
    },
    {
      "time": 1740614400,
      "open": 7.99,
      "high": 8.03,
      "low": 7.74,
      "close": 7.8,
      "volume": 331905675
    },
    {
      "time": 1740700800,
      "open": 7.75,
      "high": 7.77,
      "low": 7.49,
      "close": 7.55,
      "volume": 482692128
    },
    {
      "time": 1740960000,
      "open": 7.59,
      "high": 7.73,
      "low": 7.16,
      "close": 7.46,
      "volume": 456677093
    },
    {
      "time": 1741046400,
      "open": 7.39,
      "high": 7.64,
      "low": 7.29,
      "close": 7.43,
      "volume": 345291615
    },
    {
      "time": 1741132800,
      "open": 7.43,
      "high": 7.92,
      "low": 7.43,
      "close": 7.86,
      "volume": 381213101
    },
    {
      "time": 1741219200,
      "open": 8.0,
      "high": 8.04,
      "low": 7.7,
      "close": 7.73,
      "volume": 294304361
    },
    {
      "time": 1741305600,
      "open": 7.71,
      "high": 7.78,
      "low": 7.51,
      "close": 7.55,
      "volume": 324103970
    },
    {
      "time": 1741564800,
      "open": 7.58,
      "high": 7.64,
      "low": 7.22,
      "close": 7.26,
      "volume": 438883802
    },
    {
      "time": 1741651200,
      "open": 7.2,
      "high": 7.41,
      "low": 7.11,
      "close": 7.34,
      "volume": 334277339
    },
    {
      "time": 1741737600,
      "open": 7.32,
      "high": 7.36,
      "low": 6.87,
      "close": 7.07,
      "volume": 539372093
    },
    {
      "time": 1741824000,
      "open": 7.11,
      "high": 7.17,
      "low": 6.93,
      "close": 6.95,
      "volume": 408690029
    },
    {
      "time": 1742169600,
      "open": 7.0,
      "high": 7.08,
      "low": 6.92,
      "close": 6.94,
      "volume": 315150021
    },
    {
      "time": 1742256000,
      "open": 6.94,
      "high": 6.94,
      "low": 6.94,
      "close": 6.94,
      "volume": 0
    },
    {
      "time": 1742342400,
      "open": 7.25,
      "high": 7.72,
      "low": 7.21,
      "close": 7.44,
      "volume": 681862635
    },
    {
      "time": 1742428800,
      "open": 7.55,
      "high": 7.59,
      "low": 7.17,
      "close": 7.26,
      "volume": 475038187
    },
    {
      "time": 1742515200,
      "open": 7.28,
      "high": 7.68,
      "low": 7.24,
      "close": 7.62,
      "volume": 718941405
    },
    {
      "time": 1742774400,
      "open": 7.72,
      "high": 7.74,
      "low": 7.29,
      "close": 7.34,
      "volume": 508282460
    },
    {
      "time": 1742860800,
      "open": 7.4,
      "high": 7.43,
      "low": 7.05,
      "close": 7.15,
      "volume": 475224766
    },
    {
      "time": 1742947200,
      "open": 7.16,
      "high": 7.21,
      "low": 6.98,
      "close": 7.04,
      "volume": 579796225
    },
    {
      "time": 1743033600,
      "open": 7.01,
      "high": 7.06,
      "low": 6.87,
      "close": 6.92,
      "volume": 955968263
    },
    {
      "time": 1743120000,
      "open": 6.99,
      "high": 7.13,
      "low": 6.77,
      "close": 6.8,
      "volume": 817733412
    },
    {
      "time": 1743465600,
      "open": 7.48,
      "high": 8.56,
      "low": 7.48,
      "close": 8.1,
      "volume": 3850
    },
    {
      "time": 1743552000,
      "open": 8.31,
      "high": 8.34,
      "low": 7.94,
      "close": 8.22,
      "volume": 922157249
    },
    {
      "time": 1743638400,
      "open": 8.09,
      "high": 8.34,
      "low": 8.06,
      "close": 8.19,
      "volume": 486007460
    },
    {
      "time": 1743724800,
      "open": 8.16,
      "high": 8.18,
      "low": 7.85,
      "close": 7.91,
      "volume": 475159836
    },
    {
      "time": 1743984000,
      "open": 7.17,
      "high": 7.48,
      "low": 7.17,
      "close": 7.36,
      "volume": 683492480
    },
    {
      "time": 1744070400,
      "open": 7.51,
      "high": 7.6,
      "low": 7.14,
      "close": 7.17,
      "volume": 625885253
    },
    {
      "time": 1744156800,
      "open": 7.25,
      "high": 7.27,
      "low": 7.01,
      "close": 7.09,
      "volume": 501489583
    },
    {
      "time": 1744329600,
      "open": 7.27,
      "high": 7.29,
      "low": 7.03,
      "close": 7.17,
      "volume": 607771928
    },
    {
      "time": 1744675200,
      "open": 7.27,
      "high": 7.43,
      "low": 7.22,
      "close": 7.32,
      "volume": 494777719
    },
    {
      "time": 1744761600,
      "open": 7.32,
      "high": 7.42,
      "low": 7.23,
      "close": 7.27,
      "volume": 404503350
    },
    {
      "time": 1744848000,
      "open": 7.24,
      "high": 7.35,
      "low": 7.18,
      "close": 7.31,
      "volume": 481025151
    },
    {
      "time": 1745193600,
      "open": 7.31,
      "high": 8.19,
      "low": 7.3,
      "close": 8.07,
      "volume": 1047323375
    },
    {
      "time": 1745280000,
      "open": 8.08,
      "high": 8.11,
      "low": 7.95,
      "close": 7.97,
      "volume": 525407211
    },
    {
      "time": 1745366400,
      "open": 8.0,
      "high": 8.05,
      "low": 7.68,
      "close": 8.01,
      "volume": 514186077
    },
    {
      "time": 1745452800,
      "open": 7.94,
      "high": 8.08,
      "low": 7.9,
      "close": 7.93,
      "volume": 436243616
    },
    {
      "time": 1745539200,
      "open": 7.95,
      "high": 8.21,
      "low": 7.43,
      "close": 7.47,
      "volume": 799912461
    },
    {
      "time": 1745798400,
      "open": 7.5,
      "high": 7.57,
      "low": 7.4,
      "close": 7.45,
      "volume": 368139445
    },
    {
      "time": 1745884800,
      "open": 7.45,
      "high": 7.53,
      "low": 7.22,
      "close": 7.24,
      "volume": 443439431
    },
    {
      "time": 1745971200,
      "open": 7.25,
      "high": 7.29,
      "low": 7.1,
      "close": 7.12,
      "volume": 395244551
    },
    {
      "time": 1746144000,
      "open": 7.12,
      "high": 7.24,
      "low": 7.03,
      "close": 7.05,
      "volume": 292692534
    },
    {
      "time": 1746403200,
      "open": 7.08,
      "high": 7.18,
      "low": 7.01,
      "close": 7.15,
      "volume": 316358655
    },
    {
      "time": 1746489600,
      "open": 7.13,
      "high": 7.19,
      "low": 6.85,
      "close": 6.88,
      "volume": 398168079
    },
    {
      "time": 1746576000,
      "open": 6.77,
      "high": 6.98,
      "low": 6.75,
      "close": 6.92,
      "volume": 404491490
    },
    {
      "time": 1746662400,
      "open": 6.99,
      "high": 7.05,
      "low": 6.65,
      "close": 6.69,
      "volume": 441442626
    },
    {
      "time": 1746748800,
      "open": 6.52,
      "high": 6.74,
      "low": 6.47,
      "close": 6.7,
      "volume": 446972925
    },
    {
      "time": 1747008000,
      "open": 7.06,
      "high": 7.1,
      "low": 6.87,
      "close": 7.07,
      "volume": 414280475
    },
    {
      "time": 1747094400,
      "open": 7.01,
      "high": 7.07,
      "low": 6.93,
      "close": 6.94,
      "volume": 368589161
    },
    {
      "time": 1747180800,
      "open": 6.96,
      "high": 7.06,
      "low": 6.95,
      "close": 6.98,
      "volume": 375750045
    },
    {
      "time": 1747267200,
      "open": 7.01,
      "high": 7.27,
      "low": 6.99,
      "close": 7.23,
      "volume": 725145747
    },
    {
      "time": 1747353600,
      "open": 7.32,
      "high": 7.55,
      "low": 7.22,
      "close": 7.37,
      "volume": 680691068
    },
    {
      "time": 1747612800,
      "open": 7.19,
      "high": 7.21,
      "low": 6.48,
      "close": 6.72,
      "volume": 638470565
    },
    {
      "time": 1747699200,
      "open": 6.75,
      "high": 6.78,
      "low": 6.46,
      "close": 6.55,
      "volume": 865183265
    },
    {
      "time": 1747785600,
      "open": 6.61,
      "high": 6.8,
      "low": 6.5,
      "close": 6.76,
      "volume": 541589602
    },
    {
      "time": 1747872000,
      "open": 6.69,
      "high": 6.82,
      "low": 6.65,
      "close": 6.75,
      "volume": 390483755
    },
    {
      "time": 1747958400,
      "open": 6.73,
      "high": 6.8,
      "low": 6.69,
      "close": 6.76,
      "volume": 253857396
    },
    {
      "time": 1748217600,
      "open": 6.76,
      "high": 7.05,
      "low": 6.73,
      "close": 6.93,
      "volume": 591848002
    },
    {
      "time": 1748304000,
      "open": 6.86,
      "high": 7.05,
      "low": 6.85,
      "close": 6.96,
      "volume": 427262827
    },
    {
      "time": 1748390400,
      "open": 6.96,
      "high": 7.24,
      "low": 6.96,
      "close": 7.12,
      "volume": 611800851
    },
    {
      "time": 1748476800,
      "open": 7.12,
      "high": 7.2,
      "low": 7.1,
      "close": 7.14,
      "volume": 343185493
    },
    {
      "time": 1748563200,
      "open": 7.14,
      "high": 7.17,
      "low": 6.86,
      "close": 6.92,
      "volume": 701166432
    },
    {
      "time": 1748822400,
      "open": 6.93,
      "high": 7.1,
      "low": 6.9,
      "close": 7.03,
      "volume": 500339502
    },
    {
      "time": 1748908800,
      "open": 6.89,
      "high": 7.12,
      "low": 6.72,
      "close": 6.77,
      "volume": 679081149
    },
    {
      "time": 1748995200,
      "open": 6.77,
      "high": 6.94,
      "low": 6.65,
      "close": 6.91,
      "volume": 498825689
    },
    {
      "time": 1749081600,
      "open": 6.91,
      "high": 6.94,
      "low": 6.8,
      "close": 6.82,
      "volume": 327644690
    },
    {
      "time": 1749168000,
      "open": 6.82,
      "high": 6.95,
      "low": 6.78,
      "close": 6.92,
      "volume": 398854834
    },
    {
      "time": 1749427200,
      "open": 6.92,
      "high": 7.14,
      "low": 6.91,
      "close": 7.05,
      "volume": 630978163
    },
    {
      "time": 1749513600,
      "open": 7.05,
      "high": 7.07,
      "low": 6.94,
      "close": 6.97,
      "volume": 309411027
    },
    {
      "time": 1749600000,
      "open": 6.96,
      "high": 7.17,
      "low": 6.9,
      "close": 6.94,
      "volume": 571368131
    },
    {
      "time": 1749686400,
      "open": 7.01,
      "high": 7.01,
      "low": 6.75,
      "close": 6.78,
      "volume": 414704770
    },
    {
      "time": 1749772800,
      "open": 6.68,
      "high": 6.73,
      "low": 6.6,
      "close": 6.67,
      "volume": 469133633
    },
    {
      "time": 1750032000,
      "open": 6.67,
      "high": 6.77,
      "low": 6.47,
      "close": 6.69,
      "volume": 525509852
    },
    {
      "time": 1750118400,
      "open": 6.67,
      "high": 6.74,
      "low": 6.58,
      "close": 6.6,
      "volume": 264151825
    },
    {
      "time": 1750204800,
      "open": 6.6,
      "high": 6.7,
      "low": 6.52,
      "close": 6.56,
      "volume": 300887692
    },
    {
      "time": 1750291200,
      "open": 6.72,
      "high": 6.72,
      "low": 6.29,
      "close": 6.33,
      "volume": 641047602
    },
    {
      "time": 1750377600,
      "open": 6.35,
      "high": 6.6,
      "low": 6.32,
      "close": 6.56,
      "volume": 522945635
    },
    {
      "time": 1750636800,
      "open": 6.5,
      "high": 6.62,
      "low": 6.43,
      "close": 6.55,
      "volume": 322970787
    },
    {
      "time": 1750723200,
      "open": 6.71,
      "high": 7.03,
      "low": 6.64,
      "close": 6.86,
      "volume": 1035289031
    },
    {
      "time": 1750809600,
      "open": 6.87,
      "high": 7.27,
      "low": 6.8,
      "close": 7.13,
      "volume": 1071202528
    },
    {
      "time": 1750896000,
      "open": 7.18,
      "high": 7.35,
      "low": 7.09,
      "close": 7.24,
      "volume": 904455977
    },
    {
      "time": 1750982400,
      "open": 7.25,
      "high": 7.55,
      "low": 7.25,
      "close": 7.38,
      "volume": 805573085
    },
    {
      "time": 1751241600,
      "open": 7.4,
      "high": 7.51,
      "low": 7.32,
      "close": 7.43,
      "volume": 554256638
    },
    {
      "time": 1751328000,
      "open": 7.47,
      "high": 7.59,
      "low": 7.36,
      "close": 7.45,
      "volume": 668115067
    },
    {
      "time": 1751414400,
      "open": 7.45,
      "high": 7.6,
      "low": 7.35,
      "close": 7.52,
      "volume": 713771873
    },
    {
      "time": 1751500800,
      "open": 7.51,
      "high": 7.77,
      "low": 7.44,
      "close": 7.49,
      "volume": 711437304
    },
    {
      "time": 1751587200,
      "open": 7.48,
      "high": 7.51,
      "low": 7.33,
      "close": 7.36,
      "volume": 403035848
    },
    {
      "time": 1751846400,
      "open": 7.3,
      "high": 7.4,
      "low": 7.25,
      "close": 7.29,
      "volume": 331996862
    },
    {
      "time": 1751932800,
      "open": 7.29,
      "high": 7.37,
      "low": 7.22,
      "close": 7.29,
      "volume": 444237741
    },
    {
      "time": 1752019200,
      "open": 7.35,
      "high": 7.43,
      "low": 7.24,
      "close": 7.26,
      "volume": 340817121
    },
    {
      "time": 1752105600,
      "open": 7.32,
      "high": 7.37,
      "low": 7.26,
      "close": 7.33,
      "volume": 294420003
    },
    {
      "time": 1752192000,
      "open": 7.33,
      "high": 7.33,
      "low": 7.12,
      "close": 7.17,
      "volume": 341830457
    },
    {
      "time": 1752451200,
      "open": 7.17,
      "high": 7.77,
      "low": 7.13,
      "close": 7.71,
      "volume": 939070587
    },
    {
      "time": 1752537600,
      "open": 7.71,
      "high": 7.75,
      "low": 7.6,
      "close": 7.66,
      "volume": 342736162
    },
    {
      "time": 1752624000,
      "open": 7.65,
      "high": 7.94,
      "low": 7.55,
      "close": 7.83,
      "volume": 629952754
    },
    {
      "time": 1752710400,
      "open": 7.84,
      "high": 7.94,
      "low": 7.73,
      "close": 7.76,
      "volume": 345141447
    },
    {
      "time": 1752796800,
      "open": 7.76,
      "high": 7.8,
      "low": 7.65,
      "close": 7.72,
      "volume": 285241033
    },
    {
      "time": 1753056000,
      "open": 7.69,
      "high": 7.73,
      "low": 7.61,
      "close": 7.63,
      "volume": 228323974
    },
    {
      "time": 1753142400,
      "open": 7.63,
      "high": 7.68,
      "low": 7.34,
      "close": 7.37,
      "volume": 316468166
    },
    {
      "time": 1753228800,
      "open": 7.42,
      "high": 7.52,
      "low": 7.37,
      "close": 7.48,
      "volume": 268204946
    },
    {
      "time": 1753315200,
      "open": 7.5,
      "high": 7.54,
      "low": 7.35,
      "close": 7.37,
      "volume": 238254956
    },
    {
      "time": 1753401600,
      "open": 7.4,
      "high": 7.42,
      "low": 7.17,
      "close": 7.2,
      "volume": 298053583
    },
    {
      "time": 1753660800,
      "open": 7.24,
      "high": 7.47,
      "low": 7.1,
      "close": 7.13,
      "volume": 381288290
    },
    {
      "time": 1753747200,
      "open": 7.19,
      "high": 7.24,
      "low": 7.12,
      "close": 7.19,
      "volume": 298376818
    },
    {
      "time": 1753833600,
      "open": 7.21,
      "high": 7.24,
      "low": 6.98,
      "close": 7.0,
      "volume": 309770604
    },
    {
      "time": 1753920000,
      "open": 6.97,
      "high": 7.01,
      "low": 6.86,
      "close": 6.91,
      "volume": 355228408
    },
    {
      "time": 1754006400,
      "open": 6.9,
      "high": 6.9,
      "low": 6.55,
      "close": 6.6,
      "volume": 496324827
    },
    {
      "time": 1754265600,
      "open": 6.77,
      "high": 6.88,
      "low": 6.6,
      "close": 6.84,
      "volume": 413154881
    },
    {
      "time": 1754352000,
      "open": 6.87,
      "high": 7.01,
      "low": 6.77,
      "close": 6.91,
      "volume": 484774982
    },
    {
      "time": 1754438400,
      "open": 6.93,
      "high": 6.94,
      "low": 6.75,
      "close": 6.79,
      "volume": 259002701
    },
    {
      "time": 1754524800,
      "open": 6.76,
      "high": 6.81,
      "low": 6.6,
      "close": 6.72,
      "volume": 281870602
    },
    {
      "time": 1754611200,
      "open": 6.74,
      "high": 6.75,
      "low": 6.48,
      "close": 6.51,
      "volume": 373343824
    },
    {
      "time": 1754870400,
      "open": 6.59,
      "high": 6.64,
      "low": 6.52,
      "close": 6.6,
      "volume": 283970755
    },
    {
      "time": 1754956800,
      "open": 6.6,
      "high": 6.63,
      "low": 6.45,
      "close": 6.47,
      "volume": 317847247
    },
    {
      "time": 1755043200,
      "open": 6.53,
      "high": 6.54,
      "low": 6.35,
      "close": 6.36,
      "volume": 470360407
    },
    {
      "time": 1755129600,
      "open": 6.39,
      "high": 6.4,
      "low": 6.12,
      "close": 6.15,
      "volume": 573262165
    },
    {
      "time": 1755475200,
      "open": 6.25,
      "high": 6.69,
      "low": 6.18,
      "close": 6.46,
      "volume": 670509516
    },
    {
      "time": 1755561600,
      "open": 6.52,
      "high": 6.62,
      "low": 6.49,
      "close": 6.58,
      "volume": 353099427
    },
    {
      "time": 1755648000,
      "open": 6.61,
      "high": 6.94,
      "low": 6.57,
      "close": 6.79,
      "volume": 546082602
    },
    {
      "time": 1755734400,
      "open": 6.81,
      "high": 6.83,
      "low": 6.53,
      "close": 6.55,
      "volume": 352694732
    },
    {
      "time": 1755820800,
      "open": 6.7,
      "high": 7.31,
      "low": 6.58,
      "close": 7.07,
      "volume": 586187621
    },
    {
      "time": 1756080000,
      "open": 7.07,
      "high": 7.6,
      "low": 7.0,
      "close": 7.4,
      "volume": 92504634
    },
    {
      "time": 1756166400,
      "open": 7.1,
      "high": 7.13,
      "low": 6.6,
      "close": 6.71,
      "volume": 307771291
    },
    {
      "time": 1756339200,
      "open": 6.75,
      "high": 6.75,
      "low": 6.54,
      "close": 6.57,
      "volume": 630935008
    },
    {
      "time": 1756425600,
      "open": 6.57,
      "high": 6.76,
      "low": 6.46,
      "close": 6.49,
      "volume": 720657284
    },
    {
      "time": 1756684800,
      "open": 6.56,
      "high": 6.63,
      "low": 6.46,
      "close": 6.54,
      "volume": 449914318
    },
    {
      "time": 1756771200,
      "open": 6.55,
      "high": 6.63,
      "low": 6.5,
      "close": 6.51,
      "volume": 328932042
    },
    {
      "time": 1756857600,
      "open": 6.52,
      "high": 6.61,
      "low": 6.46,
      "close": 6.57,
      "volume": 455484219
    },
    {
      "time": 1756944000,
      "open": 6.69,
      "high": 6.94,
      "low": 6.58,
      "close": 6.61,
      "volume": 795311169
    },
    {
      "time": 1757030400,
      "open": 6.64,
      "high": 7.45,
      "low": 6.6,
      "close": 7.23,
      "volume": 645671487
    },
    {
      "time": 1757289600,
      "open": 7.45,
      "high": 7.45,
      "low": 7.17,
      "close": 7.29,
      "volume": 793222822
    },
    {
      "time": 1757376000,
      "open": 7.28,
      "high": 7.49,
      "low": 7.16,
      "close": 7.27,
      "volume": 807680182
    },
    {
      "time": 1757462400,
      "open": 7.33,
      "high": 7.51,
      "low": 7.29,
      "close": 7.32,
      "volume": 827844638
    },
    {
      "time": 1757548800,
      "open": 7.32,
      "high": 7.45,
      "low": 7.3,
      "close": 7.41,
      "volume": 521059065
    },
    {
      "time": 1757635200,
      "open": 7.44,
      "high": 7.7,
      "low": 7.42,
      "close": 7.66,
      "volume": 58262396
    },
    {
      "time": 1757894400,
      "open": 7.75,
      "high": 8.38,
      "low": 7.65,
      "close": 8.14,
      "volume": 869467952
    },
    {
      "time": 1757980800,
      "open": 8.23,
      "high": 8.24,
      "low": 7.82,
      "close": 7.94,
      "volume": 848470807
    },
    {
      "time": 1758067200,
      "open": 7.97,
      "high": 8.0,
      "low": 7.71,
      "close": 7.77,
      "volume": 587152972
    },
    {
      "time": 1758153600,
      "open": 7.79,
      "high": 7.93,
      "low": 7.72,
      "close": 7.84,
      "volume": 596497872
    },
    {
      "time": 1758240000,
      "open": 7.91,
      "high": 8.82,
      "low": 7.81,
      "close": 8.4,
      "volume": 2537
    },
    {
      "time": 1758499200,
      "open": 8.5,
      "high": 8.67,
      "low": 8.35,
      "close": 8.39,
      "volume": 886795850
    },
    {
      "time": 1758585600,
      "open": 8.39,
      "high": 8.97,
      "low": 8.35,
      "close": 8.72,
      "volume": 212226885
    },
    {
      "time": 1758672000,
      "open": 8.75,
      "high": 8.8,
      "low": 8.55,
      "close": 8.59,
      "volume": 668422957
    },
    {
      "time": 1758758400,
      "open": 8.63,
      "high": 8.84,
      "low": 8.58,
      "close": 8.68,
      "volume": 734809470
    },
    {
      "time": 1758844800,
      "open": 8.75,
      "high": 8.79,
      "low": 7.9,
      "close": 8.02,
      "volume": 523630795
    },
    {
      "time": 1759104000,
      "open": 8.06,
      "high": 8.38,
      "low": 8.02,
      "close": 8.24,
      "volume": 739155377
    },
    {
      "time": 1759190400,
      "open": 8.32,
      "high": 8.34,
      "low": 8.05,
      "close": 8.13,
      "volume": 567878004
    },
    {
      "time": 1759276800,
      "open": 8.17,
      "high": 8.58,
      "low": 8.17,
      "close": 8.52,
      "volume": 706154001
    },
    {
      "time": 1759449600,
      "open": 8.54,
      "high": 8.86,
      "low": 8.52,
      "close": 8.82,
      "volume": 721854709
    },
    {
      "time": 1759708800,
      "open": 8.95,
      "high": 8.95,
      "low": 8.33,
      "close": 8.47,
      "volume": 204329314
    },
    {
      "time": 1759795200,
      "open": 8.54,
      "high": 9.27,
      "low": 8.4,
      "close": 9.18,
      "volume": 378014525
    },
    {
      "time": 1759881600,
      "open": 9.25,
      "high": 9.4,
      "low": 9.0,
      "close": 9.04,
      "volume": 1059514161
    },
    {
      "time": 1759968000,
      "open": 9.08,
      "high": 9.28,
      "low": 8.95,
      "close": 9.03,
      "volume": 737471206
    },
    {
      "time": 1760054400,
      "open": 9.1,
      "high": 9.22,
      "low": 8.97,
      "close": 9.04,
      "volume": 701750547
    },
    {
      "time": 1760313600,
      "open": 9.02,
      "high": 9.19,
      "low": 8.67,
      "close": 8.73,
      "volume": 37230439
    },
    {
      "time": 1760400000,
      "open": 8.75,
      "high": 8.79,
      "low": 8.32,
      "close": 8.36,
      "volume": 805214355
    },
    {
      "time": 1760486400,
      "open": 8.38,
      "high": 8.82,
      "low": 8.37,
      "close": 8.75,
      "volume": 764014900
    },
    {
      "time": 1760572800,
      "open": 8.8,
      "high": 8.99,
      "low": 8.76,
      "close": 8.85,
      "volume": 583137406
    },
    {
      "time": 1760659200,
      "open": 8.85,
      "high": 8.91,
      "low": 8.66,
      "close": 8.7,
      "volume": 468590807
    },
    {
      "time": 1760918400,
      "open": 8.75,
      "high": 9.02,
      "low": 8.72,
      "close": 8.94,
      "volume": 494314718
    },
    {
      "time": 1761004800,
      "open": 9.03,
      "high": 9.06,
      "low": 8.95,
      "close": 9.0,
      "volume": 194980250
    },
    {
      "time": 1761177600,
      "open": 9.04,
      "high": 9.6,
      "low": 9.03,
      "close": 9.52,
      "volume": 222523413
    },
    {
      "time": 1761264000,
      "open": 9.52,
      "high": 9.65,
      "low": 9.25,
      "close": 9.62,
      "volume": 895335036
    },
    {
      "time": 1761523200,
      "open": 9.62,
      "high": 10.57,
      "low": 9.28,
      "close": 9.97,
      "volume": 1545
    },
    {
      "time": 1761609600,
      "open": 10.1,
      "high": 10.15,
      "low": 9.38,
      "close": 9.44,
      "volume": 383193821
    },
    {
      "time": 1761696000,
      "open": 9.51,
      "high": 9.56,
      "low": 9.27,
      "close": 9.36,
      "volume": 825914416
    },
    {
      "time": 1761782400,
      "open": 9.25,
      "high": 9.26,
      "low": 8.21,
      "close": 8.73,
      "volume": 3533
    },
    {
      "time": 1761868800,
      "open": 8.73,
      "high": 8.96,
      "low": 8.66,
      "close": 8.73,
      "volume": 779577687
    },
    {
      "time": 1762128000,
      "open": 9.15,
      "high": 9.96,
      "low": 8.76,
      "close": 9.54,
      "volume": 2544
    },
    {
      "time": 1762214400,
      "open": 9.73,
      "high": 9.76,
      "low": 9.35,
      "close": 9.41,
      "volume": 61825666
    },
    {
      "time": 1762387200,
      "open": 9.42,
      "high": 9.49,
      "low": 9.24,
      "close": 9.27,
      "volume": 731445657
    },
    {
      "time": 1762473600,
      "open": 9.27,
      "high": 9.73,
      "low": 9.2,
      "close": 9.61,
      "volume": 1723056
    },
    {
      "time": 1762732800,
      "open": 9.62,
      "high": 9.74,
      "low": 9.48,
      "close": 9.5,
      "volume": 536169122
    },
    {
      "time": 1762819200,
      "open": 9.76,
      "high": 10.33,
      "low": 9.62,
      "close": 10.24,
      "volume": 888261111
    },
    {
      "time": 1762905600,
      "open": 10.18,
      "high": 10.45,
      "low": 10.08,
      "close": 10.37,
      "volume": 25995754
    },
    {
      "time": 1762992000,
      "open": 10.3,
      "high": 10.78,
      "low": 10.27,
      "close": 10.47,
      "volume": 317392525
    },
    {
      "time": 1763078400,
      "open": 10.51,
      "high": 11.08,
      "low": 10.47,
      "close": 10.94,
      "volume": 177652422
    },
    {
      "time": 1763337600,
      "open": 11.04,
      "high": 11.06,
      "low": 10.73,
      "close": 10.93,
      "volume": 911862078
    },
    {
      "time": 1763424000,
      "open": 10.95,
      "high": 11.01,
      "low": 10.71,
      "close": 10.74,
      "volume": 612682675
    },
    {
      "time": 1763510400,
      "open": 10.75,
      "high": 10.89,
      "low": 10.58,
      "close": 10.69,
      "volume": 628320485
    },
    {
      "time": 1763596800,
      "open": 10.77,
      "high": 10.83,
      "low": 10.14,
      "close": 10.17,
      "volume": 867840425
    },
    {
      "time": 1763683200,
      "open": 10.2,
      "high": 10.29,
      "low": 9.92,
      "close": 9.97,
      "volume": 746331633
    },
    {
      "time": 1763942400,
      "open": 10.05,
      "high": 10.33,
      "low": 9.95,
      "close": 9.98,
      "volume": 675154759
    },
    {
      "time": 1764028800,
      "open": 10.02,
      "high": 10.17,
      "low": 9.94,
      "close": 10.05,
      "volume": 564921465
    },
    {
      "time": 1764115200,
      "open": 10.11,
      "high": 10.29,
      "low": 10.05,
      "close": 10.08,
      "volume": 392221239
    },
    {
      "time": 1764201600,
      "open": 10.16,
      "high": 10.29,
      "low": 10.04,
      "close": 10.11,
      "volume": 619942440
    },
    {
      "time": 1764288000,
      "open": 10.14,
      "high": 10.14,
      "low": 9.93,
      "close": 9.96,
      "volume": 456014352
    },
    {
      "time": 1764547200,
      "open": 10.0,
      "high": 10.25,
      "low": 9.75,
      "close": 9.93,
      "volume": 786869606
    },
    {
      "time": 1764633600,
      "open": 10.2,
      "high": 10.32,
      "low": 10.08,
      "close": 10.13,
      "volume": 649396924
    },
    {
      "time": 1764720000,
      "open": 10.15,
      "high": 10.6,
      "low": 10.12,
      "close": 10.55,
      "volume": 102386584
    },
    {
      "time": 1764806400,
      "open": 10.63,
      "high": 10.74,
      "low": 10.1,
      "close": 10.68,
      "volume": 126541370
    },
    {
      "time": 1764892800,
      "open": 10.57,
      "high": 10.86,
      "low": 10.4,
      "close": 10.8,
      "volume": 983988262
    },
    {
      "time": 1765152000,
      "open": 10.76,
      "high": 10.82,
      "low": 10.22,
      "close": 10.29,
      "volume": 847991012
    },
    {
      "time": 1765238400,
      "open": 10.3,
      "high": 10.81,
      "low": 10.1,
      "close": 10.74,
      "volume": 889952074
    },
    {
      "time": 1765324800,
      "open": 10.72,
      "high": 11.07,
      "low": 10.69,
      "close": 10.72,
      "volume": 688674265
    },
    {
      "time": 1765411200,
      "open": 10.74,
      "high": 11.31,
      "low": 10.7,
      "close": 11.25,
      "volume": 120953130
    },
    {
      "time": 1765497600,
      "open": 11.26,
      "high": 11.7,
      "low": 11.23,
      "close": 11.64,
      "volume": 69273659
    },
    {
      "time": 1765756800,
      "open": 11.85,
      "high": 12.03,
      "low": 11.31,
      "close": 11.35,
      "volume": 99174355
    },
    {
      "time": 1765843200,
      "open": 11.39,
      "high": 11.46,
      "low": 11.09,
      "close": 11.25,
      "volume": 712832049
    },
    {
      "time": 1765929600,
      "open": 11.25,
      "high": 11.39,
      "low": 11.06,
      "close": 11.13,
      "volume": 627013751
    },
    {
      "time": 1766016000,
      "open": 11.17,
      "high": 11.53,
      "low": 10.93,
      "close": 11.3,
      "volume": 889444084
    },
    {
      "time": 1766102400,
      "open": 11.42,
      "high": 12.0,
      "low": 11.25,
      "close": 11.96,
      "volume": 167371335
    },
    {
      "time": 1766361600,
      "open": 12.05,
      "high": 12.11,
      "low": 11.58,
      "close": 11.85,
      "volume": 1042675994
    },
    {
      "time": 1766448000,
      "open": 11.89,
      "high": 12.2,
      "low": 11.81,
      "close": 12.01,
      "volume": 1005831210
    },
    {
      "time": 1766534400,
      "open": 12.02,
      "high": 12.22,
      "low": 11.92,
      "close": 12.02,
      "volume": 606546117
    },
    {
      "time": 1766707200,
      "open": 12.0,
      "high": 12.09,
      "low": 11.89,
      "close": 11.94,
      "volume": 516916600
    },
    {
      "time": 1766966400,
      "open": 11.98,
      "high": 12.03,
      "low": 11.82,
      "close": 11.96,
      "volume": 538895837
    },
    {
      "time": 1767052800,
      "open": 11.93,
      "high": 12.19,
      "low": 11.93,
      "close": 12.06,
      "volume": 674474076
    },
    {
      "time": 1767139200,
      "open": 12.16,
      "high": 12.8,
      "low": 10.25,
      "close": 10.76,
      "volume": 1243
    },
    {
      "time": 1767225600,
      "open": 11.2,
      "high": 11.93,
      "low": 10.84,
      "close": 11.6,
      "volume": 3908
    },
    {
      "time": 1767312000,
      "open": 11.72,
      "high": 12.05,
      "low": 11.64,
      "close": 11.78,
      "volume": 372681156
    },
    {
      "time": 1767571200,
      "open": 11.8,
      "high": 12.02,
      "low": 11.36,
      "close": 11.43,
      "volume": 1008782246
    },
    {
      "time": 1767657600,
      "open": 11.46,
      "high": 11.66,
      "low": 11.32,
      "close": 11.59,
      "volume": 699559323
    },
    {
      "time": 1767744000,
      "open": 11.59,
      "high": 11.67,
      "low": 11.42,
      "close": 11.46,
      "volume": 456558352
    },
    {
      "time": 1767830400,
      "open": 11.47,
      "high": 11.63,
      "low": 11.29,
      "close": 11.5,
      "volume": 836687162
    },
    {
      "time": 1767916800,
      "open": 12.2,
      "high": 12.52,
      "low": 11.2,
      "close": 11.26,
      "volume": 1202
    },
    {
      "time": 1768176000,
      "open": 11.39,
      "high": 11.47,
      "low": 10.98,
      "close": 11.25,
      "volume": 1037070616
    },
    {
      "time": 1768262400,
      "open": 11.31,
      "high": 11.32,
      "low": 10.71,
      "close": 10.8,
      "volume": 1050929391
    },
    {
      "time": 1768348800,
      "open": 10.83,
      "high": 11.2,
      "low": 10.81,
      "close": 11.08,
      "volume": 697551451
    },
    {
      "time": 1768435200,
      "open": 11.08,
      "high": 11.08,
      "low": 11.08,
      "close": 11.08,
      "volume": 0
    },
    {
      "time": 1768521600,
      "open": 11.1,
      "high": 11.11,
      "low": 10.77,
      "close": 10.82,
      "volume": 554140658
    },
    {
      "time": 1768780800,
      "open": 10.82,
      "high": 10.82,
      "low": 10.55,
      "close": 10.59,
      "volume": 564069234
    },
    {
      "time": 1768867200,
      "open": 10.6,
      "high": 10.72,
      "low": 10.08,
      "close": 10.13,
      "volume": 737585409
    },
    {
      "time": 1768953600,
      "open": 10.13,
      "high": 10.37,
      "low": 9.92,
      "close": 10.12,
      "volume": 88780225
    },
    {
      "time": 1769040000,
      "open": 10.29,
      "high": 10.37,
      "low": 10.1,
      "close": 10.18,
      "volume": 533354101
    },
    {
      "time": 1769126400,
      "open": 10.29,
      "high": 10.29,
      "low": 9.87,
      "close": 9.93,
      "volume": 523201791
    },
    {
      "time": 1769472000,
      "open": 9.97,
      "high": 9.99,
      "low": 9.72,
      "close": 9.83,
      "volume": 566192886
    },
    {
      "time": 1769558400,
      "open": 9.93,
      "high": 10.08,
      "low": 9.76,
      "close": 9.95,
      "volume": 645264237
    },
    {
      "time": 1769644800,
      "open": 10.04,
      "high": 10.2,
      "low": 9.68,
      "close": 10.05,
      "volume": 678944962
    },
    {
      "time": 1769731200,
      "open": 9.96,
      "high": 11.38,
      "low": 9.86,
      "close": 11.17,
      "volume": 656772821
    },
    {
      "time": 1769990400,
      "open": 10.78,
      "high": 10.88,
      "low": 10.41,
      "close": 10.81,
      "volume": 693107684
    },
    {
      "time": 1770076800,
      "open": 11.02,
      "high": 11.55,
      "low": 10.81,
      "close": 11.41,
      "volume": 114976305
    },
    {
      "time": 1770163200,
      "open": 11.35,
      "high": 11.55,
      "low": 11.3,
      "close": 11.35,
      "volume": 499984642
    },
    {
      "time": 1770249600,
      "open": 11.3,
      "high": 11.4,
      "low": 11.11,
      "close": 11.24,
      "volume": 528588471
    },
    {
      "time": 1770336000,
      "open": 11.2,
      "high": 11.27,
      "low": 10.9,
      "close": 11.12,
      "volume": 579763691
    },
    {
      "time": 1770595200,
      "open": 11.3,
      "high": 11.66,
      "low": 11.23,
      "close": 11.58,
      "volume": 631894548
    },
    {
      "time": 1770681600,
      "open": 11.58,
      "high": 11.67,
      "low": 11.45,
      "close": 11.48,
      "volume": 392199772
    },
    {
      "time": 1770768000,
      "open": 11.52,
      "high": 11.9,
      "low": 11.42,
      "close": 11.85,
      "volume": 859183785
    },
    {
      "time": 1770854400,
      "open": 11.7,
      "high": 11.74,
      "low": 11.32,
      "close": 11.55,
      "volume": 497570108
    },
    {
      "time": 1770940800,
      "open": 11.44,
      "high": 11.51,
      "low": 11.26,
      "close": 11.3,
      "volume": 351653687
    },
    {
      "time": 1771200000,
      "open": 11.25,
      "high": 11.5,
      "low": 11.21,
      "close": 11.43,
      "volume": 299017626
    },
    {
      "time": 1771286400,
      "open": 11.4,
      "high": 11.46,
      "low": 11.3,
      "close": 11.38,
      "volume": 252469405
    },
    {
      "time": 1771372800,
      "open": 11.41,
      "high": 11.66,
      "low": 11.4,
      "close": 11.56,
      "volume": 358955663
    },
    {
      "time": 1771459200,
      "open": 11.6,
      "high": 11.64,
      "low": 11.14,
      "close": 11.26,
      "volume": 330114434
    },
    {
      "time": 1771545600,
      "open": 11.25,
      "high": 11.4,
      "low": 11.09,
      "close": 11.16,
      "volume": 314954760
    },
    {
      "time": 1771804800,
      "open": 11.2,
      "high": 11.22,
      "low": 10.87,
      "close": 10.98,
      "volume": 385896457
    },
    {
      "time": 1771891200,
      "open": 10.98,
      "high": 11.05,
      "low": 10.79,
      "close": 10.91,
      "volume": 385651453
    },
    {
      "time": 1771977600,
      "open": 11.01,
      "high": 11.08,
      "low": 10.69,
      "close": 10.73,
      "volume": 305829521
    },
    {
      "time": 1772064000,
      "open": 10.75,
      "high": 11.16,
      "low": 10.74,
      "close": 10.85,
      "volume": 428109099
    },
    {
      "time": 1772150400,
      "open": 10.88,
      "high": 10.94,
      "low": 10.54,
      "close": 10.59,
      "volume": 383228221
    },
    {
      "time": 1772409600,
      "open": 10.25,
      "high": 10.53,
      "low": 10.1,
      "close": 10.29,
      "volume": 498723631
    },
    {
      "time": 1772582400,
      "open": 10.1,
      "high": 10.18,
      "low": 9.85,
      "close": 9.99,
      "volume": 479791170
    },
    {
      "time": 1772668800,
      "open": 10.03,
      "high": 10.34,
      "low": 9.88,
      "close": 10.22,
      "volume": 591320459
    },
    {
      "time": 1772755200,
      "open": 10.3,
      "high": 10.38,
      "low": 10.01,
      "close": 10.06,
      "volume": 450840141
    },
    {
      "time": 1773014400,
      "open": 9.89,
      "high": 9.97,
      "low": 9.57,
      "close": 9.91,
      "volume": 414186823
    },
    {
      "time": 1773100800,
      "open": 10.01,
      "high": 10.12,
      "low": 9.86,
      "close": 10.01,
      "volume": 404894631
    },
    {
      "time": 1773187200,
      "open": 10.01,
      "high": 10.12,
      "low": 9.61,
      "close": 9.71,
      "volume": 399806526
    },
    {
      "time": 1773273600,
      "open": 9.64,
      "high": 9.74,
      "low": 9.36,
      "close": 9.56,
      "volume": 444257788
    },
    {
      "time": 1773360000,
      "open": 9.52,
      "high": 9.59,
      "low": 9.18,
      "close": 9.27,
      "volume": 570944045
    },
    {
      "time": 1773619200,
      "open": 9.32,
      "high": 9.74,
      "low": 9.29,
      "close": 9.39,
      "volume": 550904012
    },
    {
      "time": 1773705600,
      "open": 9.46,
      "high": 9.5,
      "low": 9.21,
      "close": 9.25,
      "volume": 435075957
    },
    {
      "time": 1773792000,
      "open": 9.3,
      "high": 9.54,
      "low": 9.22,
      "close": 9.44,
      "volume": 514240404
    },
    {
      "time": 1773878400,
      "open": 9.27,
      "high": 9.3,
      "low": 8.85,
      "close": 8.94,
      "volume": 636955924
    },
    {
      "time": 1773964800,
      "open": 9.05,
      "high": 9.45,
      "low": 9.05,
      "close": 9.34,
      "volume": 612165493
    },
    {
      "time": 1774224000,
      "open": 9.22,
      "high": 9.22,
      "low": 8.65,
      "close": 8.7,
      "volume": 664844250
    },
    {
      "time": 1774310400,
      "open": 9.08,
      "high": 9.08,
      "low": 8.72,
      "close": 8.88,
      "volume": 544357109
    },
    {
      "time": 1774396800,
      "open": 9.0,
      "high": 9.17,
      "low": 8.97,
      "close": 9.04,
      "volume": 437977196
    },
    {
      "time": 1774569600,
      "open": 9.0,
      "high": 9.06,
      "low": 8.84,
      "close": 8.89,
      "volume": 467368070
    },
    {
      "time": 1774828800,
      "open": 8.77,
      "high": 8.85,
      "low": 8.5,
      "close": 8.53,
      "volume": 490503989
    },
    {
      "time": 1774915200,
      "open": 8.77,
      "high": 8.85,
      "low": 8.5,
      "close": 8.54,
      "volume": 490503989
    },
    {
      "time": 1775001600,
      "open": 8.94,
      "high": 8.94,
      "low": 8.72,
      "close": 8.74,
      "volume": 256195977
    }
  ]
}